{
"meta":{"test_sets":[],"test_metrics":[],"learn_metrics":[{"best_value":"Min","name":"Logloss"}],"launch_mode":"Train","parameters":"","iteration_count":1000,"learn_sets":["learn"],"name":"experiment"},
"iterations":[
{"learn":[0.6885835184],"iteration":0,"passed_time":0.02003434837,"remaining_time":20.01431402},
{"learn":[0.683972447],"iteration":1,"passed_time":0.04481976468,"remaining_time":22.36506258},
{"learn":[0.6790248379],"iteration":2,"passed_time":0.0711702617,"remaining_time":23.6522503},
{"learn":[0.6741254301],"iteration":3,"passed_time":0.09509678352,"remaining_time":23.6790991},
{"learn":[0.6697400446],"iteration":4,"passed_time":0.1103234051,"remaining_time":21.95435761},
{"learn":[0.6643795173],"iteration":5,"passed_time":0.1239188884,"remaining_time":20.52922918},
{"learn":[0.6603543126],"iteration":6,"passed_time":0.1325228211,"remaining_time":18.79930876},
{"learn":[0.6561984549],"iteration":7,"passed_time":0.1397339496,"remaining_time":17.32700975},
{"learn":[0.6518918316],"iteration":8,"passed_time":0.1665431925,"remaining_time":18.33825597},
{"learn":[0.6470923403],"iteration":9,"passed_time":0.1869510514,"remaining_time":18.50815409},
{"learn":[0.6424768858],"iteration":10,"passed_time":0.214050327,"remaining_time":19.24507031},
{"learn":[0.638178822],"iteration":11,"passed_time":0.2297743374,"remaining_time":18.91808711},
{"learn":[0.6335301546],"iteration":12,"passed_time":0.2460147823,"remaining_time":18.67819924},
{"learn":[0.6294014625],"iteration":13,"passed_time":0.2561607697,"remaining_time":18.04103707},
{"learn":[0.6252137011],"iteration":14,"passed_time":0.269332241,"remaining_time":17.68615049},
{"learn":[0.6212616865],"iteration":15,"passed_time":0.2843735226,"remaining_time":17.48897164},
{"learn":[0.6165688252],"iteration":16,"passed_time":0.3008917882,"remaining_time":17.39862517},
{"learn":[0.6124483644],"iteration":17,"passed_time":0.3165998943,"remaining_time":17.27228312},
{"learn":[0.6091619234],"iteration":18,"passed_time":0.3273649486,"remaining_time":16.90236919},
{"learn":[0.6049530011],"iteration":19,"passed_time":0.3439559122,"remaining_time":16.8538397},
{"learn":[0.6012395925],"iteration":20,"passed_time":0.3616207156,"remaining_time":16.85841336},
{"learn":[0.5974326796],"iteration":21,"passed_time":0.3819901265,"remaining_time":16.98119744},
{"learn":[0.5941727246],"iteration":22,"passed_time":0.3958317482,"remaining_time":16.81424426},
{"learn":[0.5911321602],"iteration":23,"passed_time":0.4107866906,"remaining_time":16.70532542},
{"learn":[0.5874720852],"iteration":24,"passed_time":0.4324726064,"remaining_time":16.86643165},
{"learn":[0.5844162361],"iteration":25,"passed_time":0.4449544883,"remaining_time":16.66867968},
{"learn":[0.5814923035],"iteration":26,"passed_time":0.4561521824,"remaining_time":16.43837309},
{"learn":[0.5785055591],"iteration":27,"passed_time":0.4712258048,"remaining_time":16.35826722},
{"learn":[0.5757039035],"iteration":28,"passed_time":0.4875296032,"remaining_time":16.32383602},
{"learn":[0.5725790578],"iteration":29,"passed_time":0.5033294805,"remaining_time":16.27431987},
{"learn":[0.5697943004],"iteration":30,"passed_time":0.5149528996,"remaining_time":16.09643096},
{"learn":[0.5666123323],"iteration":31,"passed_time":0.533120909,"remaining_time":16.1269075},
{"learn":[0.5637783883],"iteration":32,"passed_time":0.5491372315,"remaining_time":16.09138494},
{"learn":[0.5607491391],"iteration":33,"passed_time":0.5644228344,"remaining_time":16.03624877},
{"learn":[0.5591852116],"iteration":34,"passed_time":0.5707640043,"remaining_time":15.73677897},
{"learn":[0.5570011844],"iteration":35,"passed_time":0.5801323289,"remaining_time":15.53465458},
{"learn":[0.5539566141],"iteration":36,"passed_time":0.5980453563,"remaining_time":15.56534265},
{"learn":[0.5520194298],"iteration":37,"passed_time":0.6135415081,"remaining_time":15.53228765},
{"learn":[0.5496177707],"iteration":38,"passed_time":0.6398815324,"remaining_time":15.76733725},
{"learn":[0.5466024027],"iteration":39,"passed_time":0.6695296753,"remaining_time":16.06871221},
{"learn":[0.5445431671],"iteration":40,"passed_time":0.6978233655,"remaining_time":16.32225872},
{"learn":[0.5419667476],"iteration":41,"passed_time":0.7316132145,"remaining_time":16.68774904},
{"learn":[0.5389838913],"iteration":42,"passed_time":0.7569375175,"remaining_time":16.84626056},
{"learn":[0.5369597456],"iteration":43,"passed_time":0.7781779274,"remaining_time":16.90768406},
{"learn":[0.5341665672],"iteration":44,"passed_time":0.8114502932,"remaining_time":17.22077845},
{"learn":[0.5326464166],"iteration":45,"passed_time":0.8297493092,"remaining_time":17.20827915},
{"learn":[0.5302085477],"iteration":46,"passed_time":0.8692474611,"remaining_time":17.62537937},
{"learn":[0.5277475412],"iteration":47,"passed_time":0.9001303011,"remaining_time":17.8525843},
{"learn":[0.525089891],"iteration":48,"passed_time":0.9206161859,"remaining_time":17.86746924},
{"learn":[0.5231590204],"iteration":49,"passed_time":0.9441892382,"remaining_time":17.93959553},
{"learn":[0.5215416574],"iteration":50,"passed_time":0.9608293473,"remaining_time":17.87896178},
{"learn":[0.5204011903],"iteration":51,"passed_time":0.9735440278,"remaining_time":17.74845651},
{"learn":[0.517844385],"iteration":52,"passed_time":1.000591484,"remaining_time":17.87849312},
{"learn":[0.5153540817],"iteration":53,"passed_time":1.026388091,"remaining_time":17.98079877},
{"learn":[0.5131430281],"iteration":54,"passed_time":1.069032202,"remaining_time":18.36791692},
{"learn":[0.5113040445],"iteration":55,"passed_time":1.100738938,"remaining_time":18.55531352},
{"learn":[0.5093933193],"iteration":56,"passed_time":1.124480331,"remaining_time":18.60324477},
{"learn":[0.5079117082],"iteration":57,"passed_time":1.134988034,"remaining_time":18.43377118},
{"learn":[0.5061200486],"iteration":58,"passed_time":1.154738481,"remaining_time":18.41710018},
{"learn":[0.5042371777],"iteration":59,"passed_time":1.172717168,"remaining_time":18.37256896},
{"learn":[0.5026140873],"iteration":60,"passed_time":1.189740547,"remaining_time":18.31420284},
{"learn":[0.5017383897],"iteration":61,"passed_time":1.196360735,"remaining_time":18.09978015},
{"learn":[0.4998078171],"iteration":62,"passed_time":1.214545381,"remaining_time":18.06395274},
{"learn":[0.4976901973],"iteration":63,"passed_time":1.234223409,"remaining_time":18.05051735},
{"learn":[0.4960551929],"iteration":64,"passed_time":1.252564809,"remaining_time":18.01766302},
{"learn":[0.4945420238],"iteration":65,"passed_time":1.26385571,"remaining_time":17.88547323},
{"learn":[0.4937529709],"iteration":66,"passed_time":1.269928193,"remaining_time":17.68422395},
{"learn":[0.4920954842],"iteration":67,"passed_time":1.289207066,"remaining_time":17.66972037},
{"learn":[0.490260551],"iteration":68,"passed_time":1.308180433,"remaining_time":17.65095627},
{"learn":[0.4889343051],"iteration":69,"passed_time":1.328007492,"remaining_time":17.64352811},
{"learn":[0.4871020084],"iteration":70,"passed_time":1.345096906,"remaining_time":17.59992993},
{"learn":[0.4860572421],"iteration":71,"passed_time":1.354565007,"remaining_time":17.45883787},
{"learn":[0.4847562595],"iteration":72,"passed_time":1.371953804,"remaining_time":17.42193392},
{"learn":[0.4840740999],"iteration":73,"passed_time":1.380028948,"remaining_time":17.26901089},
{"learn":[0.4826221508],"iteration":74,"passed_time":1.398663353,"remaining_time":17.25018136},
{"learn":[0.4808550506],"iteration":75,"passed_time":1.417717155,"remaining_time":17.23645594},
{"learn":[0.4791727396],"iteration":76,"passed_time":1.43709289,"remaining_time":17.22645113},
{"learn":[0.4781212829],"iteration":77,"passed_time":1.456458239,"remaining_time":17.21608329},
{"learn":[0.47750711],"iteration":78,"passed_time":1.464220658,"remaining_time":17.07021805},
{"learn":[0.4761653464],"iteration":79,"passed_time":1.486100381,"remaining_time":17.09015438},
{"learn":[0.4749505331],"iteration":80,"passed_time":1.506574123,"remaining_time":17.09310641},
{"learn":[0.4731619894],"iteration":81,"passed_time":1.530489443,"remaining_time":17.13401596},
{"learn":[0.4719318761],"iteration":82,"passed_time":1.556059935,"remaining_time":17.19165013},
{"learn":[0.4706350372],"iteration":83,"passed_time":1.579882594,"remaining_time":17.22824353},
{"learn":[0.4693937156],"iteration":84,"passed_time":1.606401154,"remaining_time":17.29243595},
{"learn":[0.4682674843],"iteration":85,"passed_time":1.627786266,"remaining_time":17.29996101},
{"learn":[0.4667169609],"iteration":86,"passed_time":1.647309286,"remaining_time":17.28728021},
{"learn":[0.4655323222],"iteration":87,"passed_time":1.665329146,"remaining_time":17.25886569},
{"learn":[0.4640333921],"iteration":88,"passed_time":1.684825568,"remaining_time":17.2457988},
{"learn":[0.4625931066],"iteration":89,"passed_time":1.703224813,"remaining_time":17.22149533},
{"learn":[0.461914849],"iteration":90,"passed_time":1.712940532,"remaining_time":17.1105818},
{"learn":[0.4605613874],"iteration":91,"passed_time":1.727087426,"remaining_time":17.04560199},
{"learn":[0.4597577813],"iteration":92,"passed_time":1.740633477,"remaining_time":16.97585552},
{"learn":[0.4593099536],"iteration":93,"passed_time":1.748405437,"remaining_time":16.8516524},
{"learn":[0.458250022],"iteration":94,"passed_time":1.768738423,"remaining_time":16.84956077},
{"learn":[0.4572618976],"iteration":95,"passed_time":1.786497084,"remaining_time":16.82284754},
{"learn":[0.4560336833],"iteration":96,"passed_time":1.826108865,"remaining_time":16.99975573},
{"learn":[0.4546869323],"iteration":97,"passed_time":1.858328831,"remaining_time":17.10421026},
{"learn":[0.4543976936],"iteration":98,"passed_time":1.872161946,"remaining_time":17.03856478},
{"learn":[0.4531746247],"iteration":99,"passed_time":1.901802273,"remaining_time":17.11622046},
{"learn":[0.4519054795],"iteration":100,"passed_time":1.92309959,"remaining_time":17.11749041},
{"learn":[0.450709715],"iteration":101,"passed_time":1.946710623,"remaining_time":17.13868764},
{"learn":[0.4493977429],"iteration":102,"passed_time":1.970624564,"remaining_time":17.16165276},
{"learn":[0.4482412342],"iteration":103,"passed_time":1.99583186,"remaining_time":17.1948591},
{"learn":[0.4469850769],"iteration":104,"passed_time":2.018073156,"remaining_time":17.20167118},
{"learn":[0.4465052338],"iteration":105,"passed_time":2.031851769,"remaining_time":17.13656115},
{"learn":[0.4452329097],"iteration":106,"passed_time":2.059142289,"remaining_time":17.18517817},
{"learn":[0.444568237],"iteration":107,"passed_time":2.077352639,"remaining_time":17.15739402},
{"learn":[0.4435527273],"iteration":108,"passed_time":2.094725462,"remaining_time":17.12293933},
{"learn":[0.4430782647],"iteration":109,"passed_time":2.105764746,"remaining_time":17.03755112},
{"learn":[0.4423740007],"iteration":110,"passed_time":2.128736696,"remaining_time":17.04907138},
{"learn":[0.4416054328],"iteration":111,"passed_time":2.148755713,"remaining_time":17.03656315},
{"learn":[0.4407781357],"iteration":112,"passed_time":2.167001848,"remaining_time":17.01000565},
{"learn":[0.4398776752],"iteration":113,"passed_time":2.186753764,"remaining_time":16.9952968},
{"learn":[0.4391823639],"iteration":114,"passed_time":2.200657203,"remaining_time":16.93549239},
{"learn":[0.4381481394],"iteration":115,"passed_time":2.219469448,"remaining_time":16.91388786},
{"learn":[0.4371269145],"iteration":116,"passed_time":2.23835506,"remaining_time":16.89288477},
{"learn":[0.4362319677],"iteration":117,"passed_time":2.257282872,"remaining_time":16.87223299},
{"learn":[0.4359813815],"iteration":118,"passed_time":2.270009089,"remaining_time":16.80569754},
{"learn":[0.4350525352],"iteration":119,"passed_time":2.292450705,"remaining_time":16.81130517},
{"learn":[0.4340477251],"iteration":120,"passed_time":2.313991096,"remaining_time":16.80990226},
{"learn":[0.4332289928],"iteration":121,"passed_time":2.338003434,"remaining_time":16.82595914},
{"learn":[0.4327535383],"iteration":122,"passed_time":2.354550346,"remaining_time":16.7881354},
{"learn":[0.4319093886],"iteration":123,"passed_time":2.374282288,"remaining_time":16.77315552},
{"learn":[0.431012106],"iteration":124,"passed_time":2.396744862,"remaining_time":16.77721403},
{"learn":[0.4302709416],"iteration":125,"passed_time":2.412142465,"remaining_time":16.73184535},
{"learn":[0.4294022888],"iteration":126,"passed_time":2.429341092,"remaining_time":16.69932893},
{"learn":[0.4286970844],"iteration":127,"passed_time":2.448309198,"remaining_time":16.67910641},
{"learn":[0.4277566104],"iteration":128,"passed_time":2.467178925,"remaining_time":16.6582391},
{"learn":[0.4268571897],"iteration":129,"passed_time":2.487146042,"remaining_time":16.64474659},
{"learn":[0.4260685535],"iteration":130,"passed_time":2.505463716,"remaining_time":16.62021351},
{"learn":[0.425254755],"iteration":131,"passed_time":2.523330045,"remaining_time":16.59280666},
{"learn":[0.42469042],"iteration":132,"passed_time":2.539958266,"remaining_time":16.55747231},
{"learn":[0.4243120945],"iteration":133,"passed_time":2.553417649,"remaining_time":16.50193794},
{"learn":[0.4233583034],"iteration":134,"passed_time":2.57101759,"remaining_time":16.47355715},
{"learn":[0.4231619756],"iteration":135,"passed_time":2.577531368,"remaining_time":16.37490516},
{"learn":[0.4228523553],"iteration":136,"passed_time":2.594327488,"remaining_time":16.3423695},
{"learn":[0.4219788295],"iteration":137,"passed_time":2.612636588,"remaining_time":16.3195126},
{"learn":[0.4210167346],"iteration":138,"passed_time":2.631363066,"remaining_time":16.29930647},
{"learn":[0.4201971801],"iteration":139,"passed_time":2.650992557,"remaining_time":16.28466856},
{"learn":[0.4197874193],"iteration":140,"passed_time":2.665989408,"remaining_time":16.24173689},
{"learn":[0.4191823389],"iteration":141,"passed_time":2.677901791,"remaining_time":16.18056152},
{"learn":[0.4187727493],"iteration":142,"passed_time":2.690436396,"remaining_time":16.12380413},
{"learn":[0.4179100392],"iteration":143,"passed_time":2.707172543,"remaining_time":16.09263678},
{"learn":[0.4174750057],"iteration":144,"passed_time":2.719430915,"remaining_time":16.03526505},
{"learn":[0.4169804716],"iteration":145,"passed_time":2.740786588,"remaining_time":16.03172429},
{"learn":[0.4164325535],"iteration":146,"passed_time":2.757307869,"remaining_time":15.99988852},
{"learn":[0.4161573805],"iteration":147,"passed_time":2.776222696,"remaining_time":15.98203876},
{"learn":[0.4154696281],"iteration":148,"passed_time":2.796048634,"remaining_time":15.96937844},
{"learn":[0.4151389247],"iteration":149,"passed_time":2.808099901,"remaining_time":15.91256611},
{"learn":[0.4144858642],"iteration":150,"passed_time":2.827733257,"remaining_time":15.89897706},
{"learn":[0.4140899935],"iteration":151,"passed_time":2.848750961,"remaining_time":15.89303168},
{"learn":[0.4138698828],"iteration":152,"passed_time":2.860408197,"remaining_time":15.83507021},
{"learn":[0.4131348507],"iteration":153,"passed_time":2.879316762,"remaining_time":15.81754533},
{"learn":[0.4125970149],"iteration":154,"passed_time":2.902906321,"remaining_time":15.82552156},
{"learn":[0.4123268632],"iteration":155,"passed_time":2.921434283,"remaining_time":15.80570856},
{"learn":[0.4117386747],"iteration":156,"passed_time":2.949701526,"remaining_time":15.83820628},
{"learn":[0.4112114037],"iteration":157,"passed_time":2.976650755,"remaining_time":15.86291098},
{"learn":[0.4105573297],"iteration":158,"passed_time":3.01160478,"remaining_time":15.92930579},
{"learn":[0.4105272889],"iteration":159,"passed_time":3.015683853,"remaining_time":15.83234023},
{"learn":[0.4100675402],"iteration":160,"passed_time":3.051158423,"remaining_time":15.90013613},
{"learn":[0.4099437257],"iteration":161,"passed_time":3.069449236,"remaining_time":15.87776827},
{"learn":[0.4094688432],"iteration":162,"passed_time":3.111181043,"remaining_time":15.97581922},
{"learn":[0.4090836986],"iteration":163,"passed_time":3.140732126,"remaining_time":16.01007352},
{"learn":[0.408946626],"iteration":164,"passed_time":3.16295071,"remaining_time":16.00644753},
{"learn":[0.4084719227],"iteration":165,"passed_time":3.192183254,"remaining_time":16.03783635},
{"learn":[0.4079409891],"iteration":166,"passed_time":3.220370869,"remaining_time":16.06328703},
{"learn":[0.4074455643],"iteration":167,"passed_time":3.252640851,"remaining_time":16.10831659},
{"learn":[0.4069299934],"iteration":168,"passed_time":3.271429212,"remaining_time":16.08614009},
{"learn":[0.4065485237],"iteration":169,"passed_time":3.288948888,"remaining_time":16.05780928},
{"learn":[0.40641538],"iteration":170,"passed_time":3.303735919,"remaining_time":16.01635717},
{"learn":[0.4061612161],"iteration":171,"passed_time":3.325105993,"remaining_time":16.00690559},
{"learn":[0.4058017198],"iteration":172,"passed_time":3.344464675,"remaining_time":15.98770108},
{"learn":[0.4054607948],"iteration":173,"passed_time":3.370449767,"remaining_time":15.99995119},
{"learn":[0.4051295717],"iteration":174,"passed_time":3.389397721,"remaining_time":15.97858926},
{"learn":[0.4048940055],"iteration":175,"passed_time":3.406290402,"remaining_time":15.94763234},
{"learn":[0.4047655988],"iteration":176,"passed_time":3.418646502,"remaining_time":15.89574051},
{"learn":[0.4045333093],"iteration":177,"passed_time":3.436688953,"remaining_time":15.87055236},
{"learn":[0.4039749807],"iteration":178,"passed_time":3.456809858,"remaining_time":15.85497706},
{"learn":[0.4037627121],"iteration":179,"passed_time":3.478420503,"remaining_time":15.84613785},
{"learn":[0.4032860008],"iteration":180,"passed_time":3.498328068,"remaining_time":15.82945132},
{"learn":[0.403134301],"iteration":181,"passed_time":3.509684786,"remaining_time":15.77429755},
{"learn":[0.4025613205],"iteration":182,"passed_time":3.529497146,"remaining_time":15.75737251},
{"learn":[0.4018739656],"iteration":183,"passed_time":3.547714241,"remaining_time":15.73334142},
{"learn":[0.4018076894],"iteration":184,"passed_time":3.555813887,"remaining_time":15.66480172},
{"learn":[0.4015270201],"iteration":185,"passed_time":3.574676395,"remaining_time":15.6440139},
{"learn":[0.4013008797],"iteration":186,"passed_time":3.586890119,"remaining_time":15.59434047},
{"learn":[0.4011168209],"iteration":187,"passed_time":3.596578207,"remaining_time":15.53415694},
{"learn":[0.4007483083],"iteration":188,"passed_time":3.614034277,"remaining_time":15.5078402},
{"learn":[0.4000621895],"iteration":189,"passed_time":3.631371535,"remaining_time":15.48111023},
{"learn":[0.3995796405],"iteration":190,"passed_time":3.65050749,"remaining_time":15.46209717},
{"learn":[0.3991411871],"iteration":191,"passed_time":3.672605827,"remaining_time":15.45554952},
{"learn":[0.3988899225],"iteration":192,"passed_time":3.690812362,"remaining_time":15.43256775},
{"learn":[0.3987704663],"iteration":193,"passed_time":3.700392825,"remaining_time":15.37379699},
{"learn":[0.3986005579],"iteration":194,"passed_time":3.712645175,"remaining_time":15.32656085},
{"learn":[0.3984526616],"iteration":195,"passed_time":3.727001215,"remaining_time":15.28831111},
{"learn":[0.3980057749],"iteration":196,"passed_time":3.743244599,"remaining_time":15.25799702},
{"learn":[0.3979324948],"iteration":197,"passed_time":3.749480962,"remaining_time":15.18729157},
{"learn":[0.3977652816],"iteration":198,"passed_time":3.762644591,"remaining_time":15.14511717},
{"learn":[0.3973519392],"iteration":199,"passed_time":3.779631011,"remaining_time":15.11852404},
{"learn":[0.3969228495],"iteration":200,"passed_time":3.796141797,"remaining_time":15.0901358},
{"learn":[0.3965096946],"iteration":201,"passed_time":3.818543538,"remaining_time":15.08513734},
{"learn":[0.3964235895],"iteration":202,"passed_time":3.834174448,"remaining_time":15.05338441},
{"learn":[0.3960350615],"iteration":203,"passed_time":3.859465255,"remaining_time":15.05948207},
{"learn":[0.3955632768],"iteration":204,"passed_time":3.884249738,"remaining_time":15.06330996},
{"learn":[0.3952403628],"iteration":205,"passed_time":3.905635201,"remaining_time":15.05375898},
{"learn":[0.3948763043],"iteration":206,"passed_time":3.927871232,"remaining_time":15.04735211},
{"learn":[0.3943881925],"iteration":207,"passed_time":3.948074477,"remaining_time":15.03305282},
{"learn":[0.3943370465],"iteration":208,"passed_time":3.958887094,"remaining_time":14.98315642},
{"learn":[0.3937349433],"iteration":209,"passed_time":3.979731238,"remaining_time":14.97136989},
{"learn":[0.393359491],"iteration":210,"passed_time":3.999220119,"remaining_time":14.95442974},
{"learn":[0.3932229327],"iteration":211,"passed_time":4.01814493,"remaining_time":14.93536889},
{"learn":[0.392769144],"iteration":212,"passed_time":4.04044916,"remaining_time":14.92879572},
{"learn":[0.392561771],"iteration":213,"passed_time":4.059144452,"remaining_time":14.90882028},
{"learn":[0.3922849002],"iteration":214,"passed_time":4.078659778,"remaining_time":14.89185082},
{"learn":[0.3920628572],"iteration":215,"passed_time":4.100628423,"remaining_time":14.88376243},
{"learn":[0.3918999454],"iteration":216,"passed_time":4.119410928,"remaining_time":14.86404957},
{"learn":[0.3918458052],"iteration":217,"passed_time":4.129556175,"remaining_time":14.81336206},
{"learn":[0.391333279],"iteration":218,"passed_time":4.147319628,"remaining_time":14.79021292},
{"learn":[0.3910452582],"iteration":219,"passed_time":4.179856991,"remaining_time":14.81949297},
{"learn":[0.3910356775],"iteration":220,"passed_time":4.187568734,"remaining_time":14.76070608},
{"learn":[0.3905545447],"iteration":221,"passed_time":4.220569642,"remaining_time":14.79100532},
{"learn":[0.3901660417],"iteration":222,"passed_time":4.250433069,"remaining_time":14.80980491},
{"learn":[0.3900739619],"iteration":223,"passed_time":4.284894565,"remaining_time":14.84409903},
{"learn":[0.3897643848],"iteration":224,"passed_time":4.303497854,"remaining_time":14.82315928},
{"learn":[0.3890055591],"iteration":225,"passed_time":4.325580187,"remaining_time":14.81415515},
{"learn":[0.3885530682],"iteration":226,"passed_time":4.353322654,"remaining_time":14.82431018},
{"learn":[0.3883298289],"iteration":227,"passed_time":4.379890882,"remaining_time":14.83015685},
{"learn":[0.3879727178],"iteration":228,"passed_time":4.406002694,"remaining_time":14.83418374},
{"learn":[0.3876089495],"iteration":229,"passed_time":4.428901275,"remaining_time":14.82719122},
{"learn":[0.3875624555],"iteration":230,"passed_time":4.435938259,"remaining_time":14.76725767},
{"learn":[0.3872153476],"iteration":231,"passed_time":4.450727303,"remaining_time":14.73344211},
{"learn":[0.386858282],"iteration":232,"passed_time":4.473601479,"remaining_time":14.72640487},
{"learn":[0.386376882],"iteration":233,"passed_time":4.499489964,"remaining_time":14.72909963},
{"learn":[0.3859990136],"iteration":234,"passed_time":4.523577749,"remaining_time":14.72568927},
{"learn":[0.3855077459],"iteration":235,"passed_time":4.546310445,"remaining_time":14.71771687},
{"learn":[0.3853839829],"iteration":236,"passed_time":4.561503618,"remaining_time":14.68534709},
{"learn":[0.3853161793],"iteration":237,"passed_time":4.56954126,"remaining_time":14.63021193},
{"learn":[0.3852806139],"iteration":238,"passed_time":4.57739544,"remaining_time":14.57488673},
{"learn":[0.3850671492],"iteration":239,"passed_time":4.596570944,"remaining_time":14.55580799},
{"learn":[0.3847246901],"iteration":240,"passed_time":4.616691374,"remaining_time":14.53970437},
{"learn":[0.384718219],"iteration":241,"passed_time":4.620457136,"remaining_time":14.47234095},
{"learn":[0.3846448967],"iteration":242,"passed_time":4.629641958,"remaining_time":14.42238256},
{"learn":[0.3842377107],"iteration":243,"passed_time":4.648291706,"remaining_time":14.40208414},
{"learn":[0.3841640091],"iteration":244,"passed_time":4.65789722,"remaining_time":14.35392817},
{"learn":[0.383964781],"iteration":245,"passed_time":4.677473485,"remaining_time":14.33664637},
{"learn":[0.3836317103],"iteration":246,"passed_time":4.692248088,"remaining_time":14.30470773},
{"learn":[0.3834013887],"iteration":247,"passed_time":4.709686245,"remaining_time":14.2809841},
{"learn":[0.3831097346],"iteration":248,"passed_time":4.750175028,"remaining_time":14.32683312},
{"learn":[0.3831019883],"iteration":249,"passed_time":4.758642773,"remaining_time":14.27592832},
{"learn":[0.3827829126],"iteration":250,"passed_time":4.778931761,"remaining_time":14.26063701},
{"learn":[0.3826347327],"iteration":251,"passed_time":4.798273629,"remaining_time":14.24249474},
{"learn":[0.3826293943],"iteration":252,"passed_time":4.80228893,"remaining_time":14.17909024},
{"learn":[0.3826220906],"iteration":253,"passed_time":4.809193971,"remaining_time":14.12464056},
{"learn":[0.3824420727],"iteration":254,"passed_time":4.825491029,"remaining_time":14.0980032},
{"learn":[0.3823944467],"iteration":255,"passed_time":4.840495886,"remaining_time":14.06769117},
{"learn":[0.3819833069],"iteration":256,"passed_time":4.866924878,"remaining_time":14.07052601},
{"learn":[0.3817027908],"iteration":257,"passed_time":4.889675225,"remaining_time":14.06255433},
{"learn":[0.3813915284],"iteration":258,"passed_time":4.908979952,"remaining_time":14.0446106},
{"learn":[0.3810877453],"iteration":259,"passed_time":4.930757623,"remaining_time":14.03369477},
{"learn":[0.3810767148],"iteration":260,"passed_time":4.947148885,"remaining_time":14.00744454},
{"learn":[0.3808599766],"iteration":261,"passed_time":4.970636521,"remaining_time":14.0012586},
{"learn":[0.3806316405],"iteration":262,"passed_time":4.99235523,"remaining_time":13.98998405},
{"learn":[0.3805309805],"iteration":263,"passed_time":5.010355112,"remaining_time":13.96826274},
{"learn":[0.3801772795],"iteration":264,"passed_time":5.028774207,"remaining_time":13.94773223},
{"learn":[0.3801650539],"iteration":265,"passed_time":5.037167638,"remaining_time":13.89955281},
{"learn":[0.3798874121],"iteration":266,"passed_time":5.057405045,"remaining_time":13.88418688},
{"learn":[0.3798144784],"iteration":267,"passed_time":5.069433975,"remaining_time":13.84636444},
{"learn":[0.379742911],"iteration":268,"passed_time":5.081048173,"remaining_time":13.80760675},
{"learn":[0.3794670914],"iteration":269,"passed_time":5.1025381,"remaining_time":13.79575116},
{"learn":[0.3791654699],"iteration":270,"passed_time":5.121883391,"remaining_time":13.77805532},
{"learn":[0.3788037492],"iteration":271,"passed_time":5.144270637,"remaining_time":13.76848906},
{"learn":[0.378404011],"iteration":272,"passed_time":5.164751622,"remaining_time":13.75375249},
{"learn":[0.378343847],"iteration":273,"passed_time":5.176218904,"remaining_time":13.71509096},
{"learn":[0.3779710327],"iteration":274,"passed_time":5.195589048,"remaining_time":13.69746204},
{"learn":[0.3777967306],"iteration":275,"passed_time":5.215894694,"remaining_time":13.68227449},
{"learn":[0.3775183443],"iteration":276,"passed_time":5.235768654,"remaining_time":13.66592324},
{"learn":[0.3772830421],"iteration":277,"passed_time":5.256326236,"remaining_time":13.65132209},
{"learn":[0.3770412443],"iteration":278,"passed_time":5.279405992,"remaining_time":13.64319613},
{"learn":[0.3768029987],"iteration":279,"passed_time":5.299553983,"remaining_time":13.62742453},
{"learn":[0.3764039298],"iteration":280,"passed_time":5.318119842,"remaining_time":13.60757355},
{"learn":[0.376357774],"iteration":281,"passed_time":5.345243182,"remaining_time":13.60951987},
{"learn":[0.3763416826],"iteration":282,"passed_time":5.371128307,"remaining_time":13.60812366},
{"learn":[0.3761833567],"iteration":283,"passed_time":5.413033766,"remaining_time":13.64694428},
{"learn":[0.3761805448],"iteration":284,"passed_time":5.418739295,"remaining_time":13.59438104},
{"learn":[0.3761249075],"iteration":285,"passed_time":5.441603078,"remaining_time":13.58498111},
{"learn":[0.3757837055],"iteration":286,"passed_time":5.489051988,"remaining_time":13.63656469},
{"learn":[0.3756380791],"iteration":287,"passed_time":5.531824066,"remaining_time":13.67589839},
{"learn":[0.3753725126],"iteration":288,"passed_time":5.565364356,"remaining_time":13.69195176},
{"learn":[0.3750083915],"iteration":289,"passed_time":5.608150602,"remaining_time":13.73029975},
{"learn":[0.3749345388],"iteration":290,"passed_time":5.630596679,"remaining_time":13.7185328},
{"learn":[0.3746923399],"iteration":291,"passed_time":5.656319125,"remaining_time":13.71463678},
{"learn":[0.3746627604],"iteration":292,"passed_time":5.670517598,"remaining_time":13.68278478},
{"learn":[0.3743463634],"iteration":293,"passed_time":5.722565018,"remaining_time":13.74194185},
{"learn":[0.3742478203],"iteration":294,"passed_time":5.754103089,"remaining_time":13.75133111},
{"learn":[0.3740883195],"iteration":295,"passed_time":5.781285029,"remaining_time":13.75008331},
{"learn":[0.3740104028],"iteration":296,"passed_time":5.810495833,"remaining_time":13.7534632},
{"learn":[0.3739904338],"iteration":297,"passed_time":5.822680503,"remaining_time":13.71651582},
{"learn":[0.3737548841],"iteration":298,"passed_time":5.849642885,"remaining_time":13.71438014},
{"learn":[0.3734443011],"iteration":299,"passed_time":5.879834114,"remaining_time":13.71961293},
{"learn":[0.3732730281],"iteration":300,"passed_time":5.910382174,"remaining_time":13.725439},
{"learn":[0.3732573792],"iteration":301,"passed_time":5.922779337,"remaining_time":13.68907277},
{"learn":[0.3730924878],"iteration":302,"passed_time":5.951817408,"remaining_time":13.69114433},
{"learn":[0.3728442602],"iteration":303,"passed_time":5.981805529,"remaining_time":13.69518634},
{"learn":[0.3725940974],"iteration":304,"passed_time":6.0083548,"remaining_time":13.69116913},
{"learn":[0.3725804672],"iteration":305,"passed_time":6.026325953,"remaining_time":13.66754971},
{"learn":[0.3723651817],"iteration":306,"passed_time":6.051907379,"remaining_time":13.66114597},
{"learn":[0.3720774563],"iteration":307,"passed_time":6.078479984,"remaining_time":13.65684464},
{"learn":[0.3719108595],"iteration":308,"passed_time":6.10327006,"remaining_time":13.64841298},
{"learn":[0.371631573],"iteration":309,"passed_time":6.146173379,"remaining_time":13.68019236},
{"learn":[0.3715636713],"iteration":310,"passed_time":6.172562174,"remaining_time":13.67490462},
{"learn":[0.3714538871],"iteration":311,"passed_time":6.198260543,"remaining_time":13.66795915},
{"learn":[0.3714391016],"iteration":312,"passed_time":6.21225736,"remaining_time":13.63521024},
{"learn":[0.3712991516],"iteration":313,"passed_time":6.238509609,"remaining_time":13.62935539},
{"learn":[0.3710910348],"iteration":314,"passed_time":6.268149874,"remaining_time":13.63073861},
{"learn":[0.3710176001],"iteration":315,"passed_time":6.330635225,"remaining_time":13.70302055},
{"learn":[0.3709119814],"iteration":316,"passed_time":6.38226087,"remaining_time":13.75105418},
{"learn":[0.3707534708],"iteration":317,"passed_time":6.419081438,"remaining_time":13.76670925},
{"learn":[0.3706015371],"iteration":318,"passed_time":6.444533872,"remaining_time":13.75776667},
{"learn":[0.3704365838],"iteration":319,"passed_time":6.469879103,"remaining_time":13.74849309},
{"learn":[0.3704309961],"iteration":320,"passed_time":6.480883847,"remaining_time":13.70878546},
{"learn":[0.3702201348],"iteration":321,"passed_time":6.507230729,"remaining_time":13.70156036},
{"learn":[0.3699747215],"iteration":322,"passed_time":6.531853846,"remaining_time":13.69060388},
{"learn":[0.3697657987],"iteration":323,"passed_time":6.590030914,"remaining_time":13.74957067},
{"learn":[0.3697604765],"iteration":324,"passed_time":6.603616939,"remaining_time":13.71520441},
{"learn":[0.3696485379],"iteration":325,"passed_time":6.638716616,"remaining_time":13.72544478},
{"learn":[0.369443627],"iteration":326,"passed_time":6.667656085,"remaining_time":13.7227295},
{"learn":[0.3692185881],"iteration":327,"passed_time":6.688560864,"remaining_time":13.70339299},
{"learn":[0.3690049027],"iteration":328,"passed_time":6.710611177,"remaining_time":13.68638328},
{"learn":[0.3687251481],"iteration":329,"passed_time":6.736983493,"remaining_time":13.678118},
{"learn":[0.3686395521],"iteration":330,"passed_time":6.760936632,"remaining_time":13.6648538},
{"learn":[0.3684469324],"iteration":331,"passed_time":6.784672845,"remaining_time":13.65108874},
{"learn":[0.368258645],"iteration":332,"passed_time":6.810523681,"remaining_time":13.64149938},
{"learn":[0.3680552949],"iteration":333,"passed_time":6.828634716,"remaining_time":13.6163794},
{"learn":[0.3680543366],"iteration":334,"passed_time":6.832353368,"remaining_time":13.56273131},
{"learn":[0.3677645156],"iteration":335,"passed_time":6.849607192,"remaining_time":13.5361285},
{"learn":[0.367740521],"iteration":336,"passed_time":6.867952295,"remaining_time":13.5117281},
{"learn":[0.3674960053],"iteration":337,"passed_time":6.890266709,"remaining_time":13.49513776},
{"learn":[0.3674119056],"iteration":338,"passed_time":6.906783155,"remaining_time":13.46720845},
{"learn":[0.36725566],"iteration":339,"passed_time":6.932142626,"remaining_time":13.45651216},
{"learn":[0.3671545855],"iteration":340,"passed_time":6.954967833,"remaining_time":13.44083226},
{"learn":[0.3670285546],"iteration":341,"passed_time":6.977894079,"remaining_time":13.42530498},
{"learn":[0.3667485133],"iteration":342,"passed_time":7.000592263,"remaining_time":13.40929772},
{"learn":[0.3664581437],"iteration":343,"passed_time":7.022642977,"remaining_time":13.39201684},
{"learn":[0.366321894],"iteration":344,"passed_time":7.042214835,"remaining_time":13.37000208},
{"learn":[0.366307542],"iteration":345,"passed_time":7.055715073,"remaining_time":13.33652502},
{"learn":[0.3662089664],"iteration":346,"passed_time":7.07630781,"remaining_time":13.31651009},
{"learn":[0.3658652875],"iteration":347,"passed_time":7.096245267,"remaining_time":13.29526412},
{"learn":[0.3655757764],"iteration":348,"passed_time":7.122504735,"remaining_time":13.28581829},
{"learn":[0.3652648755],"iteration":349,"passed_time":7.142222744,"remaining_time":13.26412795},
{"learn":[0.365249316],"iteration":350,"passed_time":7.148978471,"remaining_time":13.21848156},
{"learn":[0.3651006212],"iteration":351,"passed_time":7.166729433,"remaining_time":13.19329736},
{"learn":[0.3648583189],"iteration":352,"passed_time":7.190785408,"remaining_time":13.1797115},
{"learn":[0.3648577119],"iteration":353,"passed_time":7.195810957,"remaining_time":13.13133864},
{"learn":[0.3648084881],"iteration":354,"passed_time":7.211021834,"remaining_time":13.10171573},
{"learn":[0.3645300669],"iteration":355,"passed_time":7.232226005,"remaining_time":13.08301558},
{"learn":[0.364451926],"iteration":356,"passed_time":7.253259725,"remaining_time":13.06399441},
{"learn":[0.364120612],"iteration":357,"passed_time":7.273118704,"remaining_time":13.04285533},
{"learn":[0.3639973832],"iteration":358,"passed_time":7.291333402,"remaining_time":13.0187875},
{"learn":[0.3639313536],"iteration":359,"passed_time":7.302963405,"remaining_time":12.98304605},
{"learn":[0.3636541144],"iteration":360,"passed_time":7.320713273,"remaining_time":12.95827086},
{"learn":[0.3636155957],"iteration":361,"passed_time":7.334039374,"remaining_time":12.9257379},
{"learn":[0.3634939382],"iteration":362,"passed_time":7.352048834,"remaining_time":12.90152922},
{"learn":[0.3634720308],"iteration":363,"passed_time":7.361193012,"remaining_time":12.86186471},
{"learn":[0.3630933373],"iteration":364,"passed_time":7.38069316,"remaining_time":12.84038399},
{"learn":[0.3628536231],"iteration":365,"passed_time":7.399648232,"remaining_time":12.81796989},
{"learn":[0.3626709715],"iteration":366,"passed_time":7.422790335,"remaining_time":12.80279641},
{"learn":[0.3625485795],"iteration":367,"passed_time":7.446733233,"remaining_time":12.7889549},
{"learn":[0.3624537616],"iteration":368,"passed_time":7.468472013,"remaining_time":12.77128954},
{"learn":[0.362453266],"iteration":369,"passed_time":7.47724098,"remaining_time":12.73151843},
{"learn":[0.3623981872],"iteration":370,"passed_time":7.502109917,"remaining_time":12.71921061},
{"learn":[0.3623977674],"iteration":371,"passed_time":7.506171637,"remaining_time":12.67170911},
{"learn":[0.3623344777],"iteration":372,"passed_time":7.524048739,"remaining_time":12.6476637},
{"learn":[0.3620027979],"iteration":373,"passed_time":7.540974483,"remaining_time":12.62205889},
{"learn":[0.361910424],"iteration":374,"passed_time":7.555124108,"remaining_time":12.59187351},
{"learn":[0.3618643556],"iteration":375,"passed_time":7.573007907,"remaining_time":12.56797057},
{"learn":[0.3618636225],"iteration":376,"passed_time":7.580981059,"remaining_time":12.52772201},
{"learn":[0.3616662607],"iteration":377,"passed_time":7.601132983,"remaining_time":12.50768443},
{"learn":[0.3615836974],"iteration":378,"passed_time":7.613760239,"remaining_time":12.47531691},
{"learn":[0.3614415336],"iteration":379,"passed_time":7.631980982,"remaining_time":12.4521795},
{"learn":[0.3612824906],"iteration":380,"passed_time":7.651275565,"remaining_time":12.43081253},
{"learn":[0.3609817187],"iteration":381,"passed_time":7.669619398,"remaining_time":12.40791829},
{"learn":[0.3609762486],"iteration":382,"passed_time":7.679991603,"remaining_time":12.37220579},
{"learn":[0.3609374618],"iteration":383,"passed_time":7.692745543,"remaining_time":12.34044597},
{"learn":[0.3607906679],"iteration":384,"passed_time":7.718991808,"remaining_time":12.33033756},
{"learn":[0.3606720023],"iteration":385,"passed_time":7.75106488,"remaining_time":12.32941408},
{"learn":[0.3603677341],"iteration":386,"passed_time":7.782491151,"remaining_time":12.32730511},
{"learn":[0.3600300199],"iteration":387,"passed_time":7.809092423,"remaining_time":12.31743444},
{"learn":[0.3599962754],"iteration":388,"passed_time":7.836393324,"remaining_time":12.30857666},
{"learn":[0.3599124394],"iteration":389,"passed_time":7.85509782,"remaining_time":12.28617864},
{"learn":[0.359670503],"iteration":390,"passed_time":7.875891643,"remaining_time":12.26705374},
{"learn":[0.3594122913],"iteration":391,"passed_time":7.905326898,"remaining_time":12.26132335},
{"learn":[0.3593230509],"iteration":392,"passed_time":7.931411932,"remaining_time":12.25029782},
{"learn":[0.3592762226],"iteration":393,"passed_time":7.947666852,"remaining_time":12.22407643},
{"learn":[0.3591924203],"iteration":394,"passed_time":7.96521647,"remaining_time":12.19988852},
{"learn":[0.3591604107],"iteration":395,"passed_time":7.991651004,"remaining_time":12.18928587},
{"learn":[0.3590925551],"iteration":396,"passed_time":8.010600213,"remaining_time":12.16723408},
{"learn":[0.3590118095],"iteration":397,"passed_time":8.020515744,"remaining_time":12.13153386},
{"learn":[0.358863244],"iteration":398,"passed_time":8.043272294,"remaining_time":12.11530488},
{"learn":[0.3587239562],"iteration":399,"passed_time":8.071954663,"remaining_time":12.10793199},
{"learn":[0.3587235697],"iteration":400,"passed_time":8.081963546,"remaining_time":12.07255901},
{"learn":[0.3585765717],"iteration":401,"passed_time":8.108939131,"remaining_time":12.06255124},
{"learn":[0.3583480562],"iteration":402,"passed_time":8.134439693,"remaining_time":12.05027419},
{"learn":[0.3580329412],"iteration":403,"passed_time":8.156377682,"remaining_time":12.03267599},
{"learn":[0.3578036654],"iteration":404,"passed_time":8.176167752,"remaining_time":12.01190077},
{"learn":[0.3575572188],"iteration":405,"passed_time":8.194947054,"remaining_time":11.9896516},
{"learn":[0.357352508],"iteration":406,"passed_time":8.21466702,"remaining_time":11.96879003},
{"learn":[0.3572412524],"iteration":407,"passed_time":8.232583371,"remaining_time":11.94531705},
{"learn":[0.3570623866],"iteration":408,"passed_time":8.258078187,"remaining_time":11.93282203},
{"learn":[0.3570480803],"iteration":409,"passed_time":8.271690198,"remaining_time":11.90316394},
{"learn":[0.3569464324],"iteration":410,"passed_time":8.301747709,"remaining_time":11.89715183},
{"learn":[0.3569252964],"iteration":411,"passed_time":8.313175542,"remaining_time":11.864435},
{"learn":[0.3568001368],"iteration":412,"passed_time":8.342852046,"remaining_time":11.85775823},
{"learn":[0.3566042129],"iteration":413,"passed_time":8.375393284,"remaining_time":11.85502528},
{"learn":[0.3565215014],"iteration":414,"passed_time":8.402526035,"remaining_time":11.84452465},
{"learn":[0.3564411789],"iteration":415,"passed_time":8.427022191,"remaining_time":11.83024269},
{"learn":[0.3563035312],"iteration":416,"passed_time":8.446078905,"remaining_time":11.80830696},
{"learn":[0.3562637904],"iteration":417,"passed_time":8.457053668,"remaining_time":11.77513214},
{"learn":[0.3560235566],"iteration":418,"passed_time":8.474446009,"remaining_time":11.75096213},
{"learn":[0.3558419709],"iteration":419,"passed_time":8.489525716,"remaining_time":11.72363075},
{"learn":[0.3557091982],"iteration":420,"passed_time":8.506918579,"remaining_time":11.69953885},
{"learn":[0.3555513009],"iteration":421,"passed_time":8.526921852,"remaining_time":11.6790541},
{"learn":[0.3555511994],"iteration":422,"passed_time":8.529903533,"remaining_time":11.63535305},
{"learn":[0.3552839319],"iteration":423,"passed_time":8.545179109,"remaining_time":11.60854521},
{"learn":[0.3552809484],"iteration":424,"passed_time":8.550625884,"remaining_time":11.56849384},
{"learn":[0.3551448709],"iteration":425,"passed_time":8.562949892,"remaining_time":11.53787145},
{"learn":[0.354772798],"iteration":426,"passed_time":8.579354943,"remaining_time":11.5128112},
{"learn":[0.3546738781],"iteration":427,"passed_time":8.593994389,"remaining_time":11.48543175},
{"learn":[0.35459855],"iteration":428,"passed_time":8.60640354,"remaining_time":11.45514317},
{"learn":[0.3543546687],"iteration":429,"passed_time":8.624648203,"remaining_time":11.4326732},
{"learn":[0.3542532197],"iteration":430,"passed_time":8.638317324,"remaining_time":11.40418227},
{"learn":[0.3541159744],"iteration":431,"passed_time":8.652515234,"remaining_time":11.37645522},
{"learn":[0.3539890379],"iteration":432,"passed_time":8.666469398,"remaining_time":11.34847148},
{"learn":[0.3538451708],"iteration":433,"passed_time":8.681056452,"remaining_time":11.32137777},
{"learn":[0.3536686202],"iteration":434,"passed_time":8.695840895,"remaining_time":11.29459794},
{"learn":[0.3535519833],"iteration":435,"passed_time":8.712837305,"remaining_time":11.2707345},
{"learn":[0.3533551749],"iteration":436,"passed_time":8.727906851,"remaining_time":11.24442004},
{"learn":[0.3532969979],"iteration":437,"passed_time":8.741657803,"remaining_time":11.21646504},
{"learn":[0.3532072347],"iteration":438,"passed_time":8.756262439,"remaining_time":11.18966567},
{"learn":[0.3531257499],"iteration":439,"passed_time":8.775434409,"remaining_time":11.1687347},
{"learn":[0.3530074939],"iteration":440,"passed_time":8.797524082,"remaining_time":11.15151012},
{"learn":[0.3529685381],"iteration":441,"passed_time":8.814800031,"remaining_time":11.12818647},
{"learn":[0.3528805364],"iteration":442,"passed_time":8.840719204,"remaining_time":11.11575755},
{"learn":[0.3524629747],"iteration":443,"passed_time":8.865930774,"remaining_time":11.10238178},
{"learn":[0.3523787193],"iteration":444,"passed_time":8.890247886,"remaining_time":11.08783725},
{"learn":[0.3523787001],"iteration":445,"passed_time":8.894172752,"remaining_time":11.04791862},
{"learn":[0.3522523696],"iteration":446,"passed_time":8.930468966,"remaining_time":11.04820881},
{"learn":[0.3522062534],"iteration":447,"passed_time":8.956960384,"remaining_time":11.03625476},
{"learn":[0.3519125478],"iteration":448,"passed_time":8.983629135,"remaining_time":11.02445357},
{"learn":[0.3518397395],"iteration":449,"passed_time":9.006968404,"remaining_time":11.00851694},
{"learn":[0.3518397154],"iteration":450,"passed_time":9.010463308,"remaining_time":10.96839103},
{"learn":[0.3517266521],"iteration":451,"passed_time":9.030000308,"remaining_time":10.94787648},
{"learn":[0.35171992],"iteration":452,"passed_time":9.041857701,"remaining_time":10.91809307},
{"learn":[0.3516832325],"iteration":453,"passed_time":9.048745462,"remaining_time":10.88241194},
{"learn":[0.3515945616],"iteration":454,"passed_time":9.068140109,"remaining_time":10.86183815},
{"learn":[0.3513223111],"iteration":455,"passed_time":9.093676617,"remaining_time":10.84859667},
{"learn":[0.3512567389],"iteration":456,"passed_time":9.117943693,"remaining_time":10.83379305},
{"learn":[0.3511269537],"iteration":457,"passed_time":9.144597541,"remaining_time":10.82177264},
{"learn":[0.3509242494],"iteration":458,"passed_time":9.166492382,"remaining_time":10.80407926},
{"learn":[0.3508149495],"iteration":459,"passed_time":9.182589728,"remaining_time":10.77956185},
{"learn":[0.3506958575],"iteration":460,"passed_time":9.198374929,"remaining_time":10.75471602},
{"learn":[0.3506875669],"iteration":461,"passed_time":9.206503549,"remaining_time":10.72099331},
{"learn":[0.3506403561],"iteration":462,"passed_time":9.232043949,"remaining_time":10.70757581},
{"learn":[0.3504803306],"iteration":463,"passed_time":9.253826006,"remaining_time":10.68976452},
{"learn":[0.3504257924],"iteration":464,"passed_time":9.276595064,"remaining_time":10.67307174},
{"learn":[0.3503382835],"iteration":465,"passed_time":9.293488099,"remaining_time":10.64961941},
{"learn":[0.3502923922],"iteration":466,"passed_time":9.313384479,"remaining_time":10.62962297},
{"learn":[0.3502276795],"iteration":467,"passed_time":9.331553653,"remaining_time":10.60766355},
{"learn":[0.3501336495],"iteration":468,"passed_time":9.348901113,"remaining_time":10.58478996},
{"learn":[0.3500153073],"iteration":469,"passed_time":9.365692021,"remaining_time":10.56131228},
{"learn":[0.3499432976],"iteration":470,"passed_time":9.384332622,"remaining_time":10.53994046},
{"learn":[0.3498193702],"iteration":471,"passed_time":9.40036929,"remaining_time":10.51566734},
{"learn":[0.3496450588],"iteration":472,"passed_time":9.419223274,"remaining_time":10.494568},
{"learn":[0.3495900847],"iteration":473,"passed_time":9.437150459,"remaining_time":10.47244967},
{"learn":[0.3495391181],"iteration":474,"passed_time":9.450101706,"remaining_time":10.44484925},
{"learn":[0.3495140051],"iteration":475,"passed_time":9.459683551,"remaining_time":10.41360122},
{"learn":[0.3494133793],"iteration":476,"passed_time":9.477399144,"remaining_time":10.39136216},
{"learn":[0.3493755368],"iteration":477,"passed_time":9.495422959,"remaining_time":10.36947863},
{"learn":[0.3491683784],"iteration":478,"passed_time":9.512629509,"remaining_time":10.34672228},
{"learn":[0.3489961092],"iteration":479,"passed_time":9.532368252,"remaining_time":10.32673227},
{"learn":[0.3488708503],"iteration":480,"passed_time":9.550972717,"remaining_time":10.30551942},
{"learn":[0.3488558229],"iteration":481,"passed_time":9.557773345,"remaining_time":10.27163194},
{"learn":[0.3487229923],"iteration":482,"passed_time":9.575810113,"remaining_time":10.2498837},
{"learn":[0.3485969466],"iteration":483,"passed_time":9.592904008,"remaining_time":10.22714559},
{"learn":[0.3484016136],"iteration":484,"passed_time":9.609922045,"remaining_time":10.20435021},
{"learn":[0.3482763949],"iteration":485,"passed_time":9.628272442,"remaining_time":10.18298773},
{"learn":[0.3481615483],"iteration":486,"passed_time":9.645756253,"remaining_time":10.16072476},
{"learn":[0.3481587028],"iteration":487,"passed_time":9.654771359,"remaining_time":10.12959618},
{"learn":[0.3481517697],"iteration":488,"passed_time":9.666748115,"remaining_time":10.10165294},
{"learn":[0.3480585861],"iteration":489,"passed_time":9.684844675,"remaining_time":10.08014446},
{"learn":[0.3480430837],"iteration":490,"passed_time":9.695224331,"remaining_time":10.05065007},
{"learn":[0.3480411354],"iteration":491,"passed_time":9.703220994,"remaining_time":10.0187729},
{"learn":[0.3479780778],"iteration":492,"passed_time":9.723690876,"remaining_time":9.999820029},
{"learn":[0.3478532945],"iteration":493,"passed_time":9.742760202,"remaining_time":9.979426441},
{"learn":[0.3477897693],"iteration":494,"passed_time":9.760770128,"remaining_time":9.957957404},
{"learn":[0.3476960889],"iteration":495,"passed_time":9.777877226,"remaining_time":9.935584923},
{"learn":[0.3476357895],"iteration":496,"passed_time":9.793046629,"remaining_time":9.911272544},
{"learn":[0.3476120368],"iteration":497,"passed_time":9.807290465,"remaining_time":9.886063882},
{"learn":[0.3475991035],"iteration":498,"passed_time":9.816555542,"remaining_time":9.855900454},
{"learn":[0.3474986115],"iteration":499,"passed_time":9.835109331,"remaining_time":9.835109331},
{"learn":[0.3473917849],"iteration":500,"passed_time":9.856318451,"remaining_time":9.816971871},
{"learn":[0.3473898151],"iteration":501,"passed_time":9.864579286,"remaining_time":9.785977061},
{"learn":[0.3472742212],"iteration":502,"passed_time":9.885595185,"remaining_time":9.767675561},
{"learn":[0.3472497486],"iteration":503,"passed_time":9.895361008,"remaining_time":9.738291785},
{"learn":[0.3471077719],"iteration":504,"passed_time":9.912585721,"remaining_time":9.716296895},
{"learn":[0.3471060363],"iteration":505,"passed_time":9.919308585,"remaining_time":9.684068065},
{"learn":[0.347083093],"iteration":506,"passed_time":9.930401907,"remaining_time":9.656189626},
{"learn":[0.3469115017],"iteration":507,"passed_time":9.948701586,"remaining_time":9.635356654},
{"learn":[0.3468903479],"iteration":508,"passed_time":9.96019107,"remaining_time":9.607964274},
{"learn":[0.3466562109],"iteration":509,"passed_time":9.980652878,"remaining_time":9.589254726},
{"learn":[0.3466013865],"iteration":510,"passed_time":10.00225561,"remaining_time":9.571630127},
{"learn":[0.3465163297],"iteration":511,"passed_time":10.02001693,"remaining_time":9.550328634},
{"learn":[0.3463261129],"iteration":512,"passed_time":10.03846268,"remaining_time":9.529690689},
{"learn":[0.3462611106],"iteration":513,"passed_time":10.06459935,"remaining_time":9.516333239},
{"learn":[0.3462254226],"iteration":514,"passed_time":10.08968596,"remaining_time":9.50193726},
{"learn":[0.3461239527],"iteration":515,"passed_time":10.12214584,"remaining_time":9.494415861},
{"learn":[0.3460041604],"iteration":516,"passed_time":10.15537218,"remaining_time":9.487514044},
{"learn":[0.3457700165],"iteration":517,"passed_time":10.18328646,"remaining_time":9.475567708},
{"learn":[0.345660912],"iteration":518,"passed_time":10.20972624,"remaining_time":9.462193294},
{"learn":[0.3453935791],"iteration":519,"passed_time":10.24506134,"remaining_time":9.456979701},
{"learn":[0.3453547164],"iteration":520,"passed_time":10.27494788,"remaining_time":9.446641137},
{"learn":[0.3448757498],"iteration":521,"passed_time":10.3100594,"remaining_time":9.441012248},
{"learn":[0.344801749],"iteration":522,"passed_time":10.33748988,"remaining_time":9.428265145},
{"learn":[0.3446500922],"iteration":523,"passed_time":10.35451634,"remaining_time":9.406011031},
{"learn":[0.3444032903],"iteration":524,"passed_time":10.37772968,"remaining_time":9.389374474},
{"learn":[0.3443653692],"iteration":525,"passed_time":10.39091387,"remaining_time":9.363675241},
{"learn":[0.344322412],"iteration":526,"passed_time":10.40548631,"remaining_time":9.339269496},
{"learn":[0.3442854523],"iteration":527,"passed_time":10.42382496,"remaining_time":9.318267764},
{"learn":[0.3441575471],"iteration":528,"passed_time":10.44797886,"remaining_time":9.302453768},
{"learn":[0.3440691499],"iteration":529,"passed_time":10.46921371,"remaining_time":9.284019707},
{"learn":[0.3439267871],"iteration":530,"passed_time":10.49013328,"remaining_time":9.265296627},
{"learn":[0.3438977018],"iteration":531,"passed_time":10.50896763,"remaining_time":9.244730922},
{"learn":[0.3437220015],"iteration":532,"passed_time":10.52934577,"remaining_time":9.225524341},
{"learn":[0.3436405299],"iteration":533,"passed_time":10.55183032,"remaining_time":9.20815155},
{"learn":[0.3435456015],"iteration":534,"passed_time":10.57290062,"remaining_time":9.189530442},
{"learn":[0.3434882128],"iteration":535,"passed_time":10.59103256,"remaining_time":9.168356544},
{"learn":[0.3433370322],"iteration":536,"passed_time":10.6080913,"remaining_time":9.146268664},
{"learn":[0.3431772512],"iteration":537,"passed_time":10.62628165,"remaining_time":9.125171232},
{"learn":[0.3431647318],"iteration":538,"passed_time":10.63269305,"remaining_time":9.094010201},
{"learn":[0.3431360888],"iteration":539,"passed_time":10.64573735,"remaining_time":9.068591075},
{"learn":[0.3431104319],"iteration":540,"passed_time":10.65359611,"remaining_time":9.038818139},
{"learn":[0.3430310508],"iteration":541,"passed_time":10.67121221,"remaining_time":9.017371206},
{"learn":[0.3429103828],"iteration":542,"passed_time":10.68818473,"remaining_time":8.995396722},
{"learn":[0.3427947494],"iteration":543,"passed_time":10.71163731,"remaining_time":8.978872453},
{"learn":[0.3427645515],"iteration":544,"passed_time":10.73128533,"remaining_time":8.959146466},
{"learn":[0.3427305761],"iteration":545,"passed_time":10.74635538,"remaining_time":8.935614177},
{"learn":[0.3426778964],"iteration":546,"passed_time":10.76813264,"remaining_time":8.917667437},
{"learn":[0.3424982388],"iteration":547,"passed_time":10.7884249,"remaining_time":8.898481848},
{"learn":[0.342302418],"iteration":548,"passed_time":10.80987247,"remaining_time":8.880241319},
{"learn":[0.342095288],"iteration":549,"passed_time":10.82986491,"remaining_time":8.860798562},
{"learn":[0.3419482825],"iteration":550,"passed_time":10.85344335,"remaining_time":8.844275981},
{"learn":[0.341847375],"iteration":551,"passed_time":10.88388647,"remaining_time":8.83329916},
{"learn":[0.3416821007],"iteration":552,"passed_time":10.93647689,"remaining_time":8.840154016},
{"learn":[0.3416116174],"iteration":553,"passed_time":11.00105623,"remaining_time":8.856445993},
{"learn":[0.3414119239],"iteration":554,"passed_time":11.02936856,"remaining_time":8.843367581},
{"learn":[0.3412607677],"iteration":555,"passed_time":11.05404215,"remaining_time":8.827328623},
{"learn":[0.3411839208],"iteration":556,"passed_time":11.08032078,"remaining_time":8.812535195},
{"learn":[0.3411399901],"iteration":557,"passed_time":11.09217128,"remaining_time":8.786271875},
{"learn":[0.3409952806],"iteration":558,"passed_time":11.11834654,"remaining_time":8.771361044},
{"learn":[0.3409829739],"iteration":559,"passed_time":11.13262483,"remaining_time":8.74706237},
{"learn":[0.3408390752],"iteration":560,"passed_time":11.15528852,"remaining_time":8.729361247},
{"learn":[0.3408039052],"iteration":561,"passed_time":11.17497597,"remaining_time":8.709322912},
{"learn":[0.3407295287],"iteration":562,"passed_time":11.19500225,"remaining_time":8.689548813},
{"learn":[0.3406051189],"iteration":563,"passed_time":11.21397046,"remaining_time":8.668955891},
{"learn":[0.3404580725],"iteration":564,"passed_time":11.23881662,"remaining_time":8.65289421},
{"learn":[0.3403410639],"iteration":565,"passed_time":11.27373433,"remaining_time":8.644524202},
{"learn":[0.340318774],"iteration":566,"passed_time":11.28807401,"remaining_time":8.620345762},
{"learn":[0.3402044767],"iteration":567,"passed_time":11.31644872,"remaining_time":8.606876488},
{"learn":[0.3399868166],"iteration":568,"passed_time":11.34457191,"remaining_time":8.593164312},
{"learn":[0.3398087283],"iteration":569,"passed_time":11.36855024,"remaining_time":8.576274739},
{"learn":[0.3396013616],"iteration":570,"passed_time":11.39010293,"remaining_time":8.557537925},
{"learn":[0.3394603806],"iteration":571,"passed_time":11.41543962,"remaining_time":8.541622652},
{"learn":[0.3393127936],"iteration":572,"passed_time":11.43759373,"remaining_time":8.523302835},
{"learn":[0.3392989805],"iteration":573,"passed_time":11.46252714,"remaining_time":8.507032337},
{"learn":[0.3391466912],"iteration":574,"passed_time":11.49000577,"remaining_time":8.49261296},
{"learn":[0.3389708466],"iteration":575,"passed_time":11.51009831,"remaining_time":8.472711259},
{"learn":[0.3388949963],"iteration":576,"passed_time":11.52646776,"remaining_time":8.450079483},
{"learn":[0.3388266382],"iteration":577,"passed_time":11.54690774,"remaining_time":8.430441289},
{"learn":[0.338715198],"iteration":578,"passed_time":11.56598443,"remaining_time":8.409809058},
{"learn":[0.3387075993],"iteration":579,"passed_time":11.57372832,"remaining_time":8.380975677},
{"learn":[0.3386916161],"iteration":580,"passed_time":11.58552129,"remaining_time":8.355134973},
{"learn":[0.3385753379],"iteration":581,"passed_time":11.62373494,"remaining_time":8.348318222},
{"learn":[0.3383863866],"iteration":582,"passed_time":11.64562619,"remaining_time":8.329718904},
{"learn":[0.338327885],"iteration":583,"passed_time":11.66440662,"remaining_time":8.308892384},
{"learn":[0.3381910775],"iteration":584,"passed_time":11.68938447,"remaining_time":8.292469326},
{"learn":[0.3380614397],"iteration":585,"passed_time":11.71581928,"remaining_time":8.277046385},
{"learn":[0.3379419575],"iteration":586,"passed_time":11.73842406,"remaining_time":8.258891207},
{"learn":[0.3377779737],"iteration":587,"passed_time":11.76384477,"remaining_time":8.242693955},
{"learn":[0.3376308068],"iteration":588,"passed_time":11.78604302,"remaining_time":8.224216778},
{"learn":[0.3375354184],"iteration":589,"passed_time":11.8088167,"remaining_time":8.20612686},
{"learn":[0.3373562825],"iteration":590,"passed_time":11.82973785,"remaining_time":8.186739051},
{"learn":[0.3372802126],"iteration":591,"passed_time":11.8544782,"remaining_time":8.169978219},
{"learn":[0.3372680648],"iteration":592,"passed_time":11.86164839,"remaining_time":8.141131359},
{"learn":[0.3370680721],"iteration":593,"passed_time":11.88027148,"remaining_time":8.120185559},
{"learn":[0.3369641946],"iteration":594,"passed_time":11.89552961,"remaining_time":8.096957131},
{"learn":[0.3369044594],"iteration":595,"passed_time":11.90887233,"remaining_time":8.072457085},
{"learn":[0.3368433826],"iteration":596,"passed_time":11.92867009,"remaining_time":8.052351839},
{"learn":[0.3368421982],"iteration":597,"passed_time":11.93695184,"remaining_time":8.024506089},
{"learn":[0.3367453435],"iteration":598,"passed_time":11.9600455,"remaining_time":8.006641476},
{"learn":[0.3367018535],"iteration":599,"passed_time":11.97932448,"remaining_time":7.98621632},
{"learn":[0.3366110723],"iteration":600,"passed_time":12.0107063,"remaining_time":7.973829972},
{"learn":[0.3365989716],"iteration":601,"passed_time":12.0217119,"remaining_time":7.947909194},
{"learn":[0.3365568974],"iteration":602,"passed_time":12.04468031,"remaining_time":7.929913902},
{"learn":[0.3363768974],"iteration":603,"passed_time":12.06148926,"remaining_time":7.907863822},
{"learn":[0.3362993902],"iteration":604,"passed_time":12.07751796,"remaining_time":7.885321643},
{"learn":[0.3362438057],"iteration":605,"passed_time":12.09588522,"remaining_time":7.864321411},
{"learn":[0.336229682],"iteration":606,"passed_time":12.1077302,"remaining_time":7.839107031},
{"learn":[0.3360632294],"iteration":607,"passed_time":12.12767742,"remaining_time":7.819160444},
{"learn":[0.3359000366],"iteration":608,"passed_time":12.14689982,"remaining_time":7.798748487},
{"learn":[0.3358880533],"iteration":609,"passed_time":12.15419441,"remaining_time":7.770714462},
{"learn":[0.335870539],"iteration":610,"passed_time":12.16431706,"remaining_time":7.744548832},
{"learn":[0.3355635333],"iteration":611,"passed_time":12.19507914,"remaining_time":7.731520763},
{"learn":[0.3353858807],"iteration":612,"passed_time":12.22902986,"remaining_time":7.72044789},
{"learn":[0.3353555134],"iteration":613,"passed_time":12.2582496,"remaining_time":7.706326299},
{"learn":[0.3351946906],"iteration":614,"passed_time":12.28692775,"remaining_time":7.691816557},
{"learn":[0.335177492],"iteration":615,"passed_time":12.30095874,"remaining_time":7.668130125},
{"learn":[0.3351624241],"iteration":616,"passed_time":12.31592234,"remaining_time":7.645053899},
{"learn":[0.3349919349],"iteration":617,"passed_time":12.34377761,"remaining_time":7.629972568},
{"learn":[0.3349542906],"iteration":618,"passed_time":12.37159004,"remaining_time":7.614823593},
{"learn":[0.3349340379],"iteration":619,"passed_time":12.39443282,"remaining_time":7.596587855},
{"learn":[0.3349079028],"iteration":620,"passed_time":12.45284786,"remaining_time":7.600047242},
{"learn":[0.3347329924],"iteration":621,"passed_time":12.49584492,"remaining_time":7.593937908},
{"learn":[0.3346421992],"iteration":622,"passed_time":12.53234826,"remaining_time":7.58378057},
{"learn":[0.3345702343],"iteration":623,"passed_time":12.54838085,"remaining_time":7.561203848},
{"learn":[0.3344196441],"iteration":624,"passed_time":12.57899693,"remaining_time":7.547398155},
{"learn":[0.3343617638],"iteration":625,"passed_time":12.59969279,"remaining_time":7.527611986},
{"learn":[0.3342854569],"iteration":626,"passed_time":12.62371549,"remaining_time":7.509802038},
{"learn":[0.3342552299],"iteration":627,"passed_time":12.65214095,"remaining_time":7.494580308},
{"learn":[0.33416662],"iteration":628,"passed_time":12.6669016,"remaining_time":7.471256745},
{"learn":[0.3341110819],"iteration":629,"passed_time":12.69986971,"remaining_time":7.45865364},
{"learn":[0.3341084903],"iteration":630,"passed_time":12.70915517,"remaining_time":7.432136701},
{"learn":[0.3340849778],"iteration":631,"passed_time":12.72696874,"remaining_time":7.410640024},
{"learn":[0.3339281112],"iteration":632,"passed_time":12.746841,"remaining_time":7.390348573},
{"learn":[0.3338645728],"iteration":633,"passed_time":12.76715232,"remaining_time":7.370311904},
{"learn":[0.33376017],"iteration":634,"passed_time":12.78497518,"remaining_time":7.348844002},
{"learn":[0.3337594881],"iteration":635,"passed_time":12.7911748,"remaining_time":7.320735262},
{"learn":[0.3336289869],"iteration":636,"passed_time":12.80864242,"remaining_time":7.299116484},
{"learn":[0.3334207474],"iteration":637,"passed_time":12.82979036,"remaining_time":7.279598918},
{"learn":[0.3332050666],"iteration":638,"passed_time":12.84790941,"remaining_time":7.258365096},
{"learn":[0.3331175319],"iteration":639,"passed_time":12.86658269,"remaining_time":7.237452764},
{"learn":[0.3330127185],"iteration":640,"passed_time":12.88412878,"remaining_time":7.215916121},
{"learn":[0.3329050857],"iteration":641,"passed_time":12.90230383,"remaining_time":7.194742635},
{"learn":[0.3328585193],"iteration":642,"passed_time":12.91795261,"remaining_time":7.172175866},
{"learn":[0.3327665194],"iteration":643,"passed_time":12.941337,"remaining_time":7.153906789},
{"learn":[0.3326512889],"iteration":644,"passed_time":12.9616109,"remaining_time":7.133909878},
{"learn":[0.3326028052],"iteration":645,"passed_time":12.97986544,"remaining_time":7.112805522},
{"learn":[0.3323952011],"iteration":646,"passed_time":12.99618239,"remaining_time":7.090652833},
{"learn":[0.3322342074],"iteration":647,"passed_time":13.01625738,"remaining_time":7.070559565},
{"learn":[0.3320896344],"iteration":648,"passed_time":13.04154805,"remaining_time":7.053287159},
{"learn":[0.3319774325],"iteration":649,"passed_time":13.06607228,"remaining_time":7.035577382},
{"learn":[0.331716101],"iteration":650,"passed_time":13.08572917,"remaining_time":7.015237298},
{"learn":[0.3315744035],"iteration":651,"passed_time":13.10574638,"remaining_time":6.995091627},
{"learn":[0.331422666],"iteration":652,"passed_time":13.12481763,"remaining_time":6.974443674},
{"learn":[0.3314112325],"iteration":653,"passed_time":13.13229595,"remaining_time":6.947667278},
{"learn":[0.3312415034],"iteration":654,"passed_time":13.15161095,"remaining_time":6.927184395},
{"learn":[0.3309105217],"iteration":655,"passed_time":13.17170951,"remaining_time":6.907115963},
{"learn":[0.3307989936],"iteration":656,"passed_time":13.18926453,"remaining_time":6.885719534},
{"learn":[0.3306906421],"iteration":657,"passed_time":13.20616776,"remaining_time":6.863996009},
{"learn":[0.3306184113],"iteration":658,"passed_time":13.22418143,"remaining_time":6.84286171},
{"learn":[0.3305040679],"iteration":659,"passed_time":13.24317328,"remaining_time":6.82224078},
{"learn":[0.3301106841],"iteration":660,"passed_time":13.2619007,"remaining_time":6.801489164},
{"learn":[0.3299680856],"iteration":661,"passed_time":13.2803775,"remaining_time":6.780615702},
{"learn":[0.3297983394],"iteration":662,"passed_time":13.29729216,"remaining_time":6.758955441},
{"learn":[0.329651932],"iteration":663,"passed_time":13.31406868,"remaining_time":6.737239573},
{"learn":[0.3295847754],"iteration":664,"passed_time":13.3330316,"remaining_time":6.716639981},
{"learn":[0.329507427],"iteration":665,"passed_time":13.35102195,"remaining_time":6.695557556},
{"learn":[0.3294615055],"iteration":666,"passed_time":13.36319238,"remaining_time":6.671578804},
{"learn":[0.3294614996],"iteration":667,"passed_time":13.36732598,"remaining_time":6.643641058},
{"learn":[0.3292849291],"iteration":668,"passed_time":13.38363103,"remaining_time":6.621796517},
{"learn":[0.3292775874],"iteration":669,"passed_time":13.39836997,"remaining_time":6.599197147},
{"learn":[0.3291401244],"iteration":670,"passed_time":13.41671107,"remaining_time":6.578387397},
{"learn":[0.3290760897],"iteration":671,"passed_time":13.43366939,"remaining_time":6.55691006},
{"learn":[0.3289721286],"iteration":672,"passed_time":13.45166479,"remaining_time":6.535950055},
{"learn":[0.3288911968],"iteration":673,"passed_time":13.46419368,"remaining_time":6.512354807},
{"learn":[0.3288899252],"iteration":674,"passed_time":13.47222109,"remaining_time":6.486624968},
{"learn":[0.3288563776],"iteration":675,"passed_time":13.48606225,"remaining_time":6.463733977},
{"learn":[0.3287211021],"iteration":676,"passed_time":13.50324229,"remaining_time":6.442462718},
{"learn":[0.3287055595],"iteration":677,"passed_time":13.51770718,"remaining_time":6.41991403},
{"learn":[0.3286481674],"iteration":678,"passed_time":13.53629479,"remaining_time":6.399338184},
{"learn":[0.3285650635],"iteration":679,"passed_time":13.55445925,"remaining_time":6.37856906},
{"learn":[0.3284732601],"iteration":680,"passed_time":13.59048345,"remaining_time":6.366173597},
{"learn":[0.3284427475],"iteration":681,"passed_time":13.61201801,"remaining_time":6.346952677},
{"learn":[0.3284196813],"iteration":682,"passed_time":13.62595698,"remaining_time":6.324199652},
{"learn":[0.3282067028],"iteration":683,"passed_time":13.65565668,"remaining_time":6.308753672},
{"learn":[0.3281378186],"iteration":684,"passed_time":13.67882643,"remaining_time":6.290263249},
{"learn":[0.3281269792],"iteration":685,"passed_time":13.68583862,"remaining_time":6.264363449},
{"learn":[0.3280319005],"iteration":686,"passed_time":13.70388874,"remaining_time":6.243547563},
{"learn":[0.3279663935],"iteration":687,"passed_time":13.72525581,"remaining_time":6.224243914},
{"learn":[0.327874802],"iteration":688,"passed_time":13.74528853,"remaining_time":6.204331978},
{"learn":[0.3278355754],"iteration":689,"passed_time":13.78136529,"remaining_time":6.191627884},
{"learn":[0.3277373649],"iteration":690,"passed_time":13.81203192,"remaining_time":6.176436848},
{"learn":[0.327497828],"iteration":691,"passed_time":13.83258507,"remaining_time":6.156699715},
{"learn":[0.3274871567],"iteration":692,"passed_time":13.83787899,"remaining_time":6.130200359},
{"learn":[0.3273360549],"iteration":693,"passed_time":13.85960874,"remaining_time":6.111009042},
{"learn":[0.3272694404],"iteration":694,"passed_time":13.88302874,"remaining_time":6.092552179},
{"learn":[0.3272114289],"iteration":695,"passed_time":13.90603976,"remaining_time":6.073902422},
{"learn":[0.3271623861],"iteration":696,"passed_time":13.93470385,"remaining_time":6.057697657},
{"learn":[0.3271227129],"iteration":697,"passed_time":13.96363056,"remaining_time":6.041570815},
{"learn":[0.3270452444],"iteration":698,"passed_time":13.9884365,"remaining_time":6.023632884},
{"learn":[0.3268870493],"iteration":699,"passed_time":14.00861087,"remaining_time":6.003690374},
{"learn":[0.3268870002],"iteration":700,"passed_time":14.01921706,"remaining_time":5.97966605},
{"learn":[0.326732784],"iteration":701,"passed_time":14.03849107,"remaining_time":5.959359459},
{"learn":[0.3265992068],"iteration":702,"passed_time":14.05945084,"remaining_time":5.939767993},
{"learn":[0.3264849298],"iteration":703,"passed_time":14.07922178,"remaining_time":5.919672795},
{"learn":[0.3263793103],"iteration":704,"passed_time":14.09783242,"remaining_time":5.899092999},
{"learn":[0.3263754455],"iteration":705,"passed_time":14.11018091,"remaining_time":5.875911031},
{"learn":[0.3262309131],"iteration":706,"passed_time":14.12989606,"remaining_time":5.855812655},
{"learn":[0.3261565887],"iteration":707,"passed_time":14.14719911,"remaining_time":5.834720536},
{"learn":[0.3259970065],"iteration":708,"passed_time":14.16591417,"remaining_time":5.814218651},
{"learn":[0.3259864257],"iteration":709,"passed_time":14.17953218,"remaining_time":5.791639905},
{"learn":[0.3258693159],"iteration":710,"passed_time":14.20052121,"remaining_time":5.772082463},
{"learn":[0.3256114226],"iteration":711,"passed_time":14.22143169,"remaining_time":5.752489222},
{"learn":[0.3254635203],"iteration":712,"passed_time":14.24157548,"remaining_time":5.73258368},
{"learn":[0.3254635199],"iteration":713,"passed_time":14.24617582,"remaining_time":5.706451377},
{"learn":[0.3253974611],"iteration":714,"passed_time":14.27163304,"remaining_time":5.688692889},
{"learn":[0.3252804649],"iteration":715,"passed_time":14.29568185,"remaining_time":5.670354255},
{"learn":[0.3251911858],"iteration":716,"passed_time":14.31721551,"remaining_time":5.651006958},
{"learn":[0.325114536],"iteration":717,"passed_time":14.33857903,"remaining_time":5.631586752},
{"learn":[0.3250028534],"iteration":718,"passed_time":14.36039438,"remaining_time":5.612337719},
{"learn":[0.3249611347],"iteration":719,"passed_time":14.38325656,"remaining_time":5.593488663},
{"learn":[0.3248679755],"iteration":720,"passed_time":14.4046791,"remaining_time":5.574071384},
{"learn":[0.3248182855],"iteration":721,"passed_time":14.42651908,"remaining_time":5.554809285},
{"learn":[0.3246680465],"iteration":722,"passed_time":14.44659402,"remaining_time":5.534863822},
{"learn":[0.3246091563],"iteration":723,"passed_time":14.47077999,"remaining_time":5.516485191},
{"learn":[0.3245564832],"iteration":724,"passed_time":14.49179242,"remaining_time":5.496886779},
{"learn":[0.3244950124],"iteration":725,"passed_time":14.51160242,"remaining_time":5.476830665},
{"learn":[0.3243986822],"iteration":726,"passed_time":14.53029963,"remaining_time":5.456357357},
{"learn":[0.3242334066],"iteration":727,"passed_time":14.55091845,"remaining_time":5.436606894},
{"learn":[0.3241770369],"iteration":728,"passed_time":14.57119698,"remaining_time":5.416727546},
{"learn":[0.3241440967],"iteration":729,"passed_time":14.59063943,"remaining_time":5.396537871},
{"learn":[0.3240340192],"iteration":730,"passed_time":14.61196229,"remaining_time":5.377042211},
{"learn":[0.3238854166],"iteration":731,"passed_time":14.63521253,"remaining_time":5.358247209},
{"learn":[0.3238333296],"iteration":732,"passed_time":14.65667849,"remaining_time":5.33879012},
{"learn":[0.3236947452],"iteration":733,"passed_time":14.68085036,"remaining_time":5.320308169},
{"learn":[0.3235957849],"iteration":734,"passed_time":14.70252892,"remaining_time":5.300911787},
{"learn":[0.3235683],"iteration":735,"passed_time":14.73989457,"remaining_time":5.287136096},
{"learn":[0.3235490103],"iteration":736,"passed_time":14.7707952,"remaining_time":5.270989332},
{"learn":[0.3234479572],"iteration":737,"passed_time":14.80715307,"remaining_time":5.256739979},
{"learn":[0.323436961],"iteration":738,"passed_time":14.82111359,"remaining_time":5.234520497},
{"learn":[0.3233834129],"iteration":739,"passed_time":14.84913926,"remaining_time":5.217265145},
{"learn":[0.3232288468],"iteration":740,"passed_time":14.87259925,"remaining_time":5.198384892},
{"learn":[0.3231322358],"iteration":741,"passed_time":14.89733205,"remaining_time":5.179934864},
{"learn":[0.3231093511],"iteration":742,"passed_time":14.91778551,"remaining_time":5.159987721},
{"learn":[0.3229880656],"iteration":743,"passed_time":14.93962289,"remaining_time":5.140515404},
{"learn":[0.3229604406],"iteration":744,"passed_time":14.94840035,"remaining_time":5.116566563},
{"learn":[0.3229296024],"iteration":745,"passed_time":14.97924653,"remaining_time":5.100172411},
{"learn":[0.322920118],"iteration":746,"passed_time":14.9893314,"remaining_time":5.076707958},
{"learn":[0.3228454369],"iteration":747,"passed_time":15.01240105,"remaining_time":5.05765383},
{"learn":[0.3228400474],"iteration":748,"passed_time":15.01993109,"remaining_time":5.033381447},
{"learn":[0.3227681052],"iteration":749,"passed_time":15.04119567,"remaining_time":5.013731891},
{"learn":[0.3227375348],"iteration":750,"passed_time":15.06961076,"remaining_time":4.996448842},
{"learn":[0.3226312763],"iteration":751,"passed_time":15.09273627,"remaining_time":4.97739175},
{"learn":[0.3224955153],"iteration":752,"passed_time":15.1169434,"remaining_time":4.958678646},
{"learn":[0.3224300577],"iteration":753,"passed_time":15.13975068,"remaining_time":4.939494253},
{"learn":[0.3221096087],"iteration":754,"passed_time":15.15887157,"remaining_time":4.91910402},
{"learn":[0.3220243792],"iteration":755,"passed_time":15.17674039,"remaining_time":4.898313036},
{"learn":[0.3218368584],"iteration":756,"passed_time":15.19779899,"remaining_time":4.878553705},
{"learn":[0.321615838],"iteration":757,"passed_time":15.21539669,"remaining_time":4.857686016},
{"learn":[0.3216136339],"iteration":758,"passed_time":15.22719655,"remaining_time":4.834985994},
{"learn":[0.3215066667],"iteration":759,"passed_time":15.24586729,"remaining_time":4.814484406},
{"learn":[0.3213115809],"iteration":760,"passed_time":15.26921032,"remaining_time":4.795455015},
{"learn":[0.3213024906],"iteration":761,"passed_time":15.27651886,"remaining_time":4.771406153},
{"learn":[0.3212808966],"iteration":762,"passed_time":15.29129107,"remaining_time":4.749719508},
{"learn":[0.3212424233],"iteration":763,"passed_time":15.30531406,"remaining_time":4.727819525},
{"learn":[0.3212373318],"iteration":764,"passed_time":15.31193852,"remaining_time":4.703667388},
{"learn":[0.3212165825],"iteration":765,"passed_time":15.33678155,"remaining_time":4.685126479},
{"learn":[0.3210653393],"iteration":766,"passed_time":15.36568728,"remaining_time":4.667803308},
{"learn":[0.3208462207],"iteration":767,"passed_time":15.39181205,"remaining_time":4.64960989},
{"learn":[0.3208374186],"iteration":768,"passed_time":15.40128067,"remaining_time":4.626392503},
{"learn":[0.3205973269],"iteration":769,"passed_time":15.42564198,"remaining_time":4.607659293},
{"learn":[0.3205221988],"iteration":770,"passed_time":15.44953173,"remaining_time":4.588771423},
{"learn":[0.3204447011],"iteration":771,"passed_time":15.4696802,"remaining_time":4.568765656},
{"learn":[0.3203147907],"iteration":772,"passed_time":15.49019414,"remaining_time":4.548866844},
{"learn":[0.3200851526],"iteration":773,"passed_time":15.50915813,"remaining_time":4.528513873},
{"learn":[0.3200112524],"iteration":774,"passed_time":15.52827581,"remaining_time":4.508209106},
{"learn":[0.3199520689],"iteration":775,"passed_time":15.55237647,"remaining_time":4.489345784},
{"learn":[0.3198730774],"iteration":776,"passed_time":15.58752733,"remaining_time":4.473640405},
{"learn":[0.3198560443],"iteration":777,"passed_time":15.6041124,"remaining_time":4.452587342},
{"learn":[0.3197234289],"iteration":778,"passed_time":15.63032785,"remaining_time":4.434277862},
{"learn":[0.3197101877],"iteration":779,"passed_time":15.64042227,"remaining_time":4.411401153},
{"learn":[0.31962449],"iteration":780,"passed_time":15.67361054,"remaining_time":4.395032916},
{"learn":[0.3194708582],"iteration":781,"passed_time":15.704636,"remaining_time":4.378018732},
{"learn":[0.3192617868],"iteration":782,"passed_time":15.73634367,"remaining_time":4.361157823},
{"learn":[0.3191298469],"iteration":783,"passed_time":15.76693722,"remaining_time":4.34395209},
{"learn":[0.3191168423],"iteration":784,"passed_time":15.79839316,"remaining_time":4.326948446},
{"learn":[0.3190415322],"iteration":785,"passed_time":15.8235248,"remaining_time":4.308186143},
{"learn":[0.3189720942],"iteration":786,"passed_time":15.84913035,"remaining_time":4.289535914},
{"learn":[0.3189431882],"iteration":787,"passed_time":15.87141024,"remaining_time":4.269973313},
{"learn":[0.3187930656],"iteration":788,"passed_time":15.90528008,"remaining_time":4.253503291},
{"learn":[0.3187661527],"iteration":789,"passed_time":15.92836853,"remaining_time":4.234123281},
{"learn":[0.3186905116],"iteration":790,"passed_time":15.96714906,"remaining_time":4.218880093},
{"learn":[0.3186635919],"iteration":791,"passed_time":16.00334912,"remaining_time":4.202899768},
{"learn":[0.3186459157],"iteration":792,"passed_time":16.02587043,"remaining_time":4.183297829},
{"learn":[0.318434958],"iteration":793,"passed_time":16.05244055,"remaining_time":4.164738984},
{"learn":[0.3182561049],"iteration":794,"passed_time":16.08552688,"remaining_time":4.147840263},
{"learn":[0.3181074486],"iteration":795,"passed_time":16.1163107,"remaining_time":4.130310784},
{"learn":[0.3180942734],"iteration":796,"passed_time":16.14046354,"remaining_time":4.111059095},
{"learn":[0.3180524863],"iteration":797,"passed_time":16.16879434,"remaining_time":4.092852703},
{"learn":[0.3180392894],"iteration":798,"passed_time":16.18030495,"remaining_time":4.070389606},
{"learn":[0.3179422012],"iteration":799,"passed_time":16.19784842,"remaining_time":4.049462106},
{"learn":[0.3178554082],"iteration":800,"passed_time":16.22232172,"remaining_time":4.030264698},
{"learn":[0.317687857],"iteration":801,"passed_time":16.24451108,"remaining_time":4.010490267},
{"learn":[0.3174465238],"iteration":802,"passed_time":16.26884998,"remaining_time":3.991237168},
{"learn":[0.3172508913],"iteration":803,"passed_time":16.29381763,"remaining_time":3.972124697},
{"learn":[0.3171980239],"iteration":804,"passed_time":16.31588425,"remaining_time":3.952294944},
{"learn":[0.3170524969],"iteration":805,"passed_time":16.33813019,"remaining_time":3.932502799},
{"learn":[0.3170111799],"iteration":806,"passed_time":16.35665473,"remaining_time":3.911814576},
{"learn":[0.3167777132],"iteration":807,"passed_time":16.37835888,"remaining_time":3.891887259},
{"learn":[0.3167697118],"iteration":808,"passed_time":16.38720724,"remaining_time":3.868920374},
{"learn":[0.3166064279],"iteration":809,"passed_time":16.42865929,"remaining_time":3.85363613},
{"learn":[0.316598489],"iteration":810,"passed_time":16.43732514,"remaining_time":3.830646672},
{"learn":[0.3165906253],"iteration":811,"passed_time":16.44245701,"remaining_time":3.806874284},
{"learn":[0.3165827386],"iteration":812,"passed_time":16.45237187,"remaining_time":3.784247896},
{"learn":[0.3165783461],"iteration":813,"passed_time":16.46178712,"remaining_time":3.761538581},
{"learn":[0.3165285725],"iteration":814,"passed_time":16.48084155,"remaining_time":3.741049922},
{"learn":[0.3164053101],"iteration":815,"passed_time":16.50219717,"remaining_time":3.721083676},
{"learn":[0.3163659007],"iteration":816,"passed_time":16.52384973,"remaining_time":3.701180538},
{"learn":[0.3162479644],"iteration":817,"passed_time":16.54365788,"remaining_time":3.680862755},
{"learn":[0.3162356471],"iteration":818,"passed_time":16.5639603,"remaining_time":3.660655451},
{"learn":[0.3160422498],"iteration":819,"passed_time":16.58843271,"remaining_time":3.641363278},
{"learn":[0.3159469255],"iteration":820,"passed_time":16.61419714,"remaining_time":3.622340181},
{"learn":[0.3159003202],"iteration":821,"passed_time":16.63742698,"remaining_time":3.602751828},
{"learn":[0.3158684045],"iteration":822,"passed_time":16.66173588,"remaining_time":3.583386695},
{"learn":[0.3157614214],"iteration":823,"passed_time":16.68454417,"remaining_time":3.563689045},
{"learn":[0.3157440921],"iteration":824,"passed_time":16.69978777,"remaining_time":3.542379223},
{"learn":[0.3155926689],"iteration":825,"passed_time":16.72035689,"remaining_time":3.52220593},
{"learn":[0.3155191944],"iteration":826,"passed_time":16.74167605,"remaining_time":3.502188581},
{"learn":[0.315316796],"iteration":827,"passed_time":16.76279231,"remaining_time":3.482125938},
{"learn":[0.3151349311],"iteration":828,"passed_time":16.78608897,"remaining_time":3.462510512},
{"learn":[0.3151137108],"iteration":829,"passed_time":16.79600737,"remaining_time":3.440146088},
{"learn":[0.3151095669],"iteration":830,"passed_time":16.80277546,"remaining_time":3.417170942},
{"learn":[0.3150440763],"iteration":831,"passed_time":16.8213012,"remaining_time":3.396608897},
{"learn":[0.3149246711],"iteration":832,"passed_time":16.84253224,"remaining_time":3.376594099},
{"learn":[0.3147602523],"iteration":833,"passed_time":16.86125869,"remaining_time":3.356077869},
{"learn":[0.3146815917],"iteration":834,"passed_time":16.8794525,"remaining_time":3.335460673},
{"learn":[0.3146122912],"iteration":835,"passed_time":16.89886941,"remaining_time":3.315089215},
{"learn":[0.3144419501],"iteration":836,"passed_time":16.91722453,"remaining_time":3.29451326},
{"learn":[0.3144310526],"iteration":837,"passed_time":16.92458743,"remaining_time":3.271817619},
{"learn":[0.3142363984],"iteration":838,"passed_time":16.94276888,"remaining_time":3.251234552},
{"learn":[0.3142231696],"iteration":839,"passed_time":16.95709202,"remaining_time":3.22992229},
{"learn":[0.3140535926],"iteration":840,"passed_time":16.97533902,"remaining_time":3.209368496},
{"learn":[0.313966396],"iteration":841,"passed_time":16.99929302,"remaining_time":3.189891089},
{"learn":[0.3139222183],"iteration":842,"passed_time":17.02512378,"remaining_time":3.17075259},
{"learn":[0.3138812291],"iteration":843,"passed_time":17.05051255,"remaining_time":3.151516537},
{"learn":[0.3137600059],"iteration":844,"passed_time":17.07899326,"remaining_time":3.132833084},
{"learn":[0.3136392686],"iteration":845,"passed_time":17.11967343,"remaining_time":3.116347173},
{"learn":[0.3136184088],"iteration":846,"passed_time":17.14905006,"remaining_time":3.097762289},
{"learn":[0.3134156026],"iteration":847,"passed_time":17.19175652,"remaining_time":3.081541264},
{"learn":[0.313370066],"iteration":848,"passed_time":17.2419614,"remaining_time":3.066591486},
{"learn":[0.3132694992],"iteration":849,"passed_time":17.29474626,"remaining_time":3.052014047},
{"learn":[0.3130931394],"iteration":850,"passed_time":17.33605315,"remaining_time":3.035337155},
{"learn":[0.3130077728],"iteration":851,"passed_time":17.36199949,"remaining_time":3.015934184},
{"learn":[0.3128774544],"iteration":852,"passed_time":17.37825176,"remaining_time":2.994845262},
{"learn":[0.3128514128],"iteration":853,"passed_time":17.40380461,"remaining_time":2.975357698},
{"learn":[0.3128370167],"iteration":854,"passed_time":17.43309955,"remaining_time":2.956490567},
{"learn":[0.312606619],"iteration":855,"passed_time":17.46547411,"remaining_time":2.938117139},
{"learn":[0.3124748475],"iteration":856,"passed_time":17.49851769,"remaining_time":2.919822671},
{"learn":[0.3123342521],"iteration":857,"passed_time":17.52884944,"remaining_time":2.901045012},
{"learn":[0.3123194338],"iteration":858,"passed_time":17.55831188,"remaining_time":2.882097759},
{"learn":[0.3120737162],"iteration":859,"passed_time":17.58841977,"remaining_time":2.863231125},
{"learn":[0.3119032859],"iteration":860,"passed_time":17.61911438,"remaining_time":2.844433099},
{"learn":[0.3116156637],"iteration":861,"passed_time":17.65082558,"remaining_time":2.825770221},
{"learn":[0.3115549557],"iteration":862,"passed_time":17.68171882,"remaining_time":2.806947251},
{"learn":[0.3114585092],"iteration":863,"passed_time":17.70930182,"remaining_time":2.787575287},
{"learn":[0.3114404673],"iteration":864,"passed_time":17.73304081,"remaining_time":2.767584403},
{"learn":[0.3113875261],"iteration":865,"passed_time":17.75941445,"remaining_time":2.747992536},
{"learn":[0.3113806554],"iteration":866,"passed_time":17.77063502,"remaining_time":2.726060505},
{"learn":[0.3111593881],"iteration":867,"passed_time":17.80148737,"remaining_time":2.707138632},
{"learn":[0.3111083986],"iteration":868,"passed_time":17.8288888,"remaining_time":2.687669082},
{"learn":[0.3109535972],"iteration":869,"passed_time":17.85967409,"remaining_time":2.668686934},
{"learn":[0.31089955],"iteration":870,"passed_time":17.88811539,"remaining_time":2.649330523},
{"learn":[0.3106891781],"iteration":871,"passed_time":17.91616197,"remaining_time":2.629895335},
{"learn":[0.3106891076],"iteration":872,"passed_time":17.92721915,"remaining_time":2.60796888},
{"learn":[0.3106593321],"iteration":873,"passed_time":17.95797516,"remaining_time":2.588907174},
{"learn":[0.3105742406],"iteration":874,"passed_time":17.98947868,"remaining_time":2.569925526},
{"learn":[0.3105320246],"iteration":875,"passed_time":18.01972417,"remaining_time":2.550737211},
{"learn":[0.310411469],"iteration":876,"passed_time":18.04814686,"remaining_time":2.531268032},
{"learn":[0.3103717521],"iteration":877,"passed_time":18.07928521,"remaining_time":2.512155804},
{"learn":[0.3103045153],"iteration":878,"passed_time":18.10575896,"remaining_time":2.4923741},
{"learn":[0.3102175169],"iteration":879,"passed_time":18.12949961,"remaining_time":2.472204492},
{"learn":[0.310211103],"iteration":880,"passed_time":18.1393388,"remaining_time":2.450149055},
{"learn":[0.3101406816],"iteration":881,"passed_time":18.16934267,"remaining_time":2.430819087},
{"learn":[0.3100276695],"iteration":882,"passed_time":18.19950988,"remaining_time":2.411486587},
{"learn":[0.3099413514],"iteration":883,"passed_time":18.22749906,"remaining_time":2.391843768},
{"learn":[0.3097847595],"iteration":884,"passed_time":18.25562291,"remaining_time":2.372199587},
{"learn":[0.3097234638],"iteration":885,"passed_time":18.32434735,"remaining_time":2.357760269},
{"learn":[0.3095186795],"iteration":886,"passed_time":18.37162793,"remaining_time":2.340466693},
{"learn":[0.3094226139],"iteration":887,"passed_time":18.40256879,"remaining_time":2.321044712},
{"learn":[0.3094030079],"iteration":888,"passed_time":18.44225649,"remaining_time":2.302688943},
{"learn":[0.3093329435],"iteration":889,"passed_time":18.47614139,"remaining_time":2.283568036},
{"learn":[0.309244212],"iteration":890,"passed_time":18.5256198,"remaining_time":2.266321615},
{"learn":[0.3091362126],"iteration":891,"passed_time":18.55358263,"remaining_time":2.246397897},
{"learn":[0.3090325738],"iteration":892,"passed_time":18.58520078,"remaining_time":2.226894158},
{"learn":[0.3089190284],"iteration":893,"passed_time":18.62482518,"remaining_time":2.208312605},
{"learn":[0.3088415193],"iteration":894,"passed_time":18.67409524,"remaining_time":2.190815643},
{"learn":[0.3085523707],"iteration":895,"passed_time":18.71676577,"remaining_time":2.172481742},
{"learn":[0.3083275259],"iteration":896,"passed_time":18.74984114,"remaining_time":2.152991792},
{"learn":[0.3081767627],"iteration":897,"passed_time":18.77161601,"remaining_time":2.13218801},
{"learn":[0.3080452381],"iteration":898,"passed_time":18.79376201,"remaining_time":2.111423763},
{"learn":[0.3079673327],"iteration":899,"passed_time":18.81481995,"remaining_time":2.09053555},
{"learn":[0.3078675517],"iteration":900,"passed_time":18.83474451,"remaining_time":2.069522426},
{"learn":[0.3077311714],"iteration":901,"passed_time":18.85629247,"remaining_time":2.048688095},
{"learn":[0.3076438814],"iteration":902,"passed_time":18.87525796,"remaining_time":2.027574775},
{"learn":[0.3075878582],"iteration":903,"passed_time":18.89844351,"remaining_time":2.006914355},
{"learn":[0.3075010513],"iteration":904,"passed_time":18.92077415,"remaining_time":1.986158613},
{"learn":[0.3073336878],"iteration":905,"passed_time":18.94025945,"remaining_time":1.965104181},
{"learn":[0.307146756],"iteration":906,"passed_time":18.95941419,"remaining_time":1.944019316},
{"learn":[0.3071409914],"iteration":907,"passed_time":18.96576814,"remaining_time":1.921641706},
{"learn":[0.3070987263],"iteration":908,"passed_time":18.98615896,"remaining_time":1.900704583},
{"learn":[0.3069945966],"iteration":909,"passed_time":19.01092038,"remaining_time":1.880200917},
{"learn":[0.3067567596],"iteration":910,"passed_time":19.03535029,"remaining_time":1.859655517},
{"learn":[0.3065944141],"iteration":911,"passed_time":19.06061264,"remaining_time":1.839181922},
{"learn":[0.3064640125],"iteration":912,"passed_time":19.09081181,"remaining_time":1.819168267},
{"learn":[0.3063721545],"iteration":913,"passed_time":19.11629848,"remaining_time":1.798688916},
{"learn":[0.306238211],"iteration":914,"passed_time":19.14028216,"remaining_time":1.778058998},
{"learn":[0.3061356847],"iteration":915,"passed_time":19.16500403,"remaining_time":1.757489453},
{"learn":[0.3059854964],"iteration":916,"passed_time":19.18906519,"remaining_time":1.736851048},
{"learn":[0.3059623473],"iteration":917,"passed_time":19.21216595,"remaining_time":1.716119399},
{"learn":[0.3058109604],"iteration":918,"passed_time":19.23226972,"remaining_time":1.695118441},
{"learn":[0.3057798918],"iteration":919,"passed_time":19.24846834,"remaining_time":1.673779855},
{"learn":[0.3056869979],"iteration":920,"passed_time":19.26790995,"remaining_time":1.652730604},
{"learn":[0.3055301241],"iteration":921,"passed_time":19.28601096,"remaining_time":1.631571426},
{"learn":[0.3054827054],"iteration":922,"passed_time":19.31316707,"remaining_time":1.611174284},
{"learn":[0.3054475964],"iteration":923,"passed_time":19.33761622,"remaining_time":1.590539862},
{"learn":[0.305345268],"iteration":924,"passed_time":19.3593011,"remaining_time":1.569673062},
{"learn":[0.3053399272],"iteration":925,"passed_time":19.3672197,"remaining_time":1.547704382},
{"learn":[0.3053002108],"iteration":926,"passed_time":19.38910183,"remaining_time":1.526865624},
{"learn":[0.3051738821],"iteration":927,"passed_time":19.40949274,"remaining_time":1.505908919},
{"learn":[0.3050031787],"iteration":928,"passed_time":19.42861548,"remaining_time":1.484856511},
{"learn":[0.3047963764],"iteration":929,"passed_time":19.46589376,"remaining_time":1.465174799},
{"learn":[0.3047912253],"iteration":930,"passed_time":19.47375516,"remaining_time":1.443275087},
{"learn":[0.3047455433],"iteration":931,"passed_time":19.51267893,"remaining_time":1.423671853},
{"learn":[0.3047297851],"iteration":932,"passed_time":19.54540652,"remaining_time":1.403582248},
{"learn":[0.3047050597],"iteration":933,"passed_time":19.56797045,"remaining_time":1.382747377},
{"learn":[0.3045567181],"iteration":934,"passed_time":19.58556301,"remaining_time":1.361563204},
{"learn":[0.3045004683],"iteration":935,"passed_time":19.61685296,"remaining_time":1.341323279},
{"learn":[0.3044059792],"iteration":936,"passed_time":19.64030171,"remaining_time":1.320532559},
{"learn":[0.3041770387],"iteration":937,"passed_time":19.66747431,"remaining_time":1.299982311},
{"learn":[0.304141721],"iteration":938,"passed_time":19.69832649,"remaining_time":1.279656992},
{"learn":[0.3040788686],"iteration":939,"passed_time":19.71354082,"remaining_time":1.258311116},
{"learn":[0.3040554229],"iteration":940,"passed_time":19.72846486,"remaining_time":1.236960071},
{"learn":[0.3039486229],"iteration":941,"passed_time":19.75307094,"remaining_time":1.216218805},
{"learn":[0.3038755841],"iteration":942,"passed_time":19.77326397,"remaining_time":1.195202594},
{"learn":[0.3038707184],"iteration":943,"passed_time":19.7812203,"remaining_time":1.173462221},
{"learn":[0.303684834],"iteration":944,"passed_time":19.80304933,"remaining_time":1.152558427},
{"learn":[0.3034487162],"iteration":945,"passed_time":19.8227022,"remaining_time":1.131528455},
{"learn":[0.3033811666],"iteration":946,"passed_time":19.84170675,"remaining_time":1.110465108},
{"learn":[0.3033752173],"iteration":947,"passed_time":19.84803579,"remaining_time":1.088710824},
{"learn":[0.3033577971],"iteration":948,"passed_time":19.86456293,"remaining_time":1.067537102},
{"learn":[0.3033326909],"iteration":949,"passed_time":19.88184861,"remaining_time":1.046413085},
{"learn":[0.3032386327],"iteration":950,"passed_time":19.90323516,"remaining_time":1.025508436},
{"learn":[0.3031556126],"iteration":951,"passed_time":19.92141751,"remaining_time":1.004441219},
{"learn":[0.3030305349],"iteration":952,"passed_time":19.93915611,"remaining_time":0.9833581712},
{"learn":[0.302932355],"iteration":953,"passed_time":19.95729469,"remaining_time":0.9623014211},
{"learn":[0.3026298507],"iteration":954,"passed_time":19.97575836,"remaining_time":0.9412661009},
{"learn":[0.3024648692],"iteration":955,"passed_time":19.99360844,"remaining_time":0.92020792},
{"learn":[0.3023634064],"iteration":956,"passed_time":20.01362761,"remaining_time":0.8992539052},
{"learn":[0.3019495895],"iteration":957,"passed_time":20.03103377,"remaining_time":0.8781872842},
{"learn":[0.3019175692],"iteration":958,"passed_time":20.05073602,"remaining_time":0.8572264619},
{"learn":[0.3017954306],"iteration":959,"passed_time":20.0684748,"remaining_time":0.8361864502},
{"learn":[0.3016425748],"iteration":960,"passed_time":20.08710994,"remaining_time":0.8151896852},
{"learn":[0.3015124036],"iteration":961,"passed_time":20.10542563,"remaining_time":0.7941852121},
{"learn":[0.3012758715],"iteration":962,"passed_time":20.12829836,"remaining_time":0.7733614116},
{"learn":[0.3012129794],"iteration":963,"passed_time":20.15043503,"remaining_time":0.7525058725},
{"learn":[0.3010602828],"iteration":964,"passed_time":20.17233194,"remaining_time":0.7316389821},
{"learn":[0.3010499697],"iteration":965,"passed_time":20.1825854,"remaining_time":0.7103601486},
{"learn":[0.3008905385],"iteration":966,"passed_time":20.20132265,"remaining_time":0.6893936375},
{"learn":[0.3008463976],"iteration":967,"passed_time":20.21587701,"remaining_time":0.6682934549},
{"learn":[0.3007399739],"iteration":968,"passed_time":20.23650037,"remaining_time":0.6474009406},
{"learn":[0.3006604099],"iteration":969,"passed_time":20.25559563,"remaining_time":0.6264617205},
{"learn":[0.3005040596],"iteration":970,"passed_time":20.27466214,"remaining_time":0.6055254399},
{"learn":[0.3004619468],"iteration":971,"passed_time":20.29276998,"remaining_time":0.5845653903},
{"learn":[0.300444626],"iteration":972,"passed_time":20.31151269,"remaining_time":0.5636288208},
{"learn":[0.3003720607],"iteration":973,"passed_time":20.33185963,"remaining_time":0.5427395796},
{"learn":[0.3002810167],"iteration":974,"passed_time":20.35015887,"remaining_time":0.5217989455},
{"learn":[0.3002081109],"iteration":975,"passed_time":20.36888392,"remaining_time":0.5008741947},
{"learn":[0.3001202479],"iteration":976,"passed_time":20.38833995,"remaining_time":0.4799711553},
{"learn":[0.2999442269],"iteration":977,"passed_time":20.40598182,"remaining_time":0.4590302658},
{"learn":[0.2998617359],"iteration":978,"passed_time":20.42262884,"remaining_time":0.438074776},
{"learn":[0.2997902637],"iteration":979,"passed_time":20.44365436,"remaining_time":0.4172174359},
{"learn":[0.2996808593],"iteration":980,"passed_time":20.46201128,"remaining_time":0.3963080676},
{"learn":[0.2996710819],"iteration":981,"passed_time":20.47211268,"remaining_time":0.3752525747},
{"learn":[0.299589575],"iteration":982,"passed_time":20.4895149,"remaining_time":0.3543456289},
{"learn":[0.2995218476],"iteration":983,"passed_time":20.50723092,"remaining_time":0.3334509092},
{"learn":[0.2995157945],"iteration":984,"passed_time":20.51883625,"remaining_time":0.3124695876},
{"learn":[0.2993927062],"iteration":985,"passed_time":20.53887642,"remaining_time":0.2916270486},
{"learn":[0.2993696172],"iteration":986,"passed_time":20.55674441,"remaining_time":0.2707575251},
{"learn":[0.2993029436],"iteration":987,"passed_time":20.57675613,"remaining_time":0.249920115},
{"learn":[0.2991083999],"iteration":988,"passed_time":20.5999437,"remaining_time":0.2291196973},
{"learn":[0.2990484264],"iteration":989,"passed_time":20.640212,"remaining_time":0.2084869899},
{"learn":[0.2989818118],"iteration":990,"passed_time":20.67083531,"remaining_time":0.1877270614},
{"learn":[0.2988695125],"iteration":991,"passed_time":20.69667441,"remaining_time":0.1669086646},
{"learn":[0.2987944026],"iteration":992,"passed_time":20.72616331,"remaining_time":0.1461058844},
{"learn":[0.2986882612],"iteration":993,"passed_time":20.74841723,"remaining_time":0.1252419551},
{"learn":[0.2986159385],"iteration":994,"passed_time":20.77124387,"remaining_time":0.1043781099},
{"learn":[0.2985030451],"iteration":995,"passed_time":20.79489858,"remaining_time":0.08351364893},
{"learn":[0.2981945813],"iteration":996,"passed_time":20.8161188,"remaining_time":0.06263626519},
{"learn":[0.2981665039],"iteration":997,"passed_time":20.84489598,"remaining_time":0.04177333864},
{"learn":[0.2981057152],"iteration":998,"passed_time":20.86882598,"remaining_time":0.02088971569},
{"learn":[0.2980248841],"iteration":999,"passed_time":20.88409002,"remaining_time":0}
]}